<?xml version="1.0" encoding="UTF-8" standalone="yes"?>
<ns8:AIXMBasicMessage ns1:id="cf956499-afce-4dbe-a7b1-6d432566cc12" xmlns:ns6="http://www.isotc211.org/2005/gmd" xmlns:ns5="http://www.isotc211.org/2005/gmx" xmlns:ns8="http://www.aixm.aero/schema/5.1/message" xmlns:ns7="http://www.isotc211.org/2005/gts" xmlns:ns2="http://www.w3.org/1999/xlink" xmlns:ns1="http://www.opengis.net/gml/3.2" xmlns:ns4="http://www.isotc211.org/2005/gco" xmlns:ns3="http://www.aixm.aero/schema/5.1">
    <ns1:description ns2:type="simple">IND_MVA_FUS3_2022</ns1:description>
    <ns1:boundedBy xsi:nil="true" xmlns:xsi="http://www.w3.org/2001/XMLSchema-instance"/>
    <ns3:sequenceNumber>1</ns3:sequenceNumber>
    <ns3:messageMetadata/>
    <ns8:hasMember ns2:type="simple">
        <ns3:Airspace ns1:id="19329684">
            <ns1:description ns2:type="simple">MINIMUM VECTORING ALTITUDE (MVA)</ns1:description>
            <ns1:boundedBy xsi:nil="true" xmlns:xsi="http://www.w3.org/2001/XMLSchema-instance"/>
            <ns3:timeSlice>
                <ns3:AirspaceTimeSlice>
                    <ns1:validTime ns2:type="simple">
                        <ns1:TimePeriod>
                            <ns1:beginPosition>1980-01-01T14:00:00Z</ns1:beginPosition>
                            <ns1:endPosition indeterminatePosition="unknown"/>
                        </ns1:TimePeriod>
                    </ns1:validTime>
                    <ns3:interpretation>BASELINE</ns3:interpretation>
                    <ns3:sequenceNumber>1</ns3:sequenceNumber>
                    <ns3:type>OTHER</ns3:type>
                    <ns3:designator xsi:nil="true" xmlns:xsi="http://www.w3.org/2001/XMLSchema-instance"/>
                    <ns3:localType xsi:nil="true" xmlns:xsi="http://www.w3.org/2001/XMLSchema-instance"/>
                    <ns3:name>A</ns3:name>
                    <ns3:designatorICAO xsi:nil="true" xmlns:xsi="http://www.w3.org/2001/XMLSchema-instance"/>
                    <ns3:controlType xsi:nil="true" xmlns:xsi="http://www.w3.org/2001/XMLSchema-instance"/>
                    <ns3:upperLowerSeparation xsi:nil="true" xmlns:xsi="http://www.w3.org/2001/XMLSchema-instance"/>
                    <ns3:protectedRoute xsi:nil="true" xmlns:xsi="http://www.w3.org/2001/XMLSchema-instance"/>
                    <ns3:geometryComponent>
                        <ns3:AirspaceGeometryComponent>
                            <ns3:operation xsi:nil="true" xmlns:xsi="http://www.w3.org/2001/XMLSchema-instance"/>
                            <ns3:operationSequence xsi:nil="true" xmlns:xsi="http://www.w3.org/2001/XMLSchema-instance"/>
                            <ns3:theAirspaceVolume>
                                <ns3:AirspaceVolume>
                                    <ns3:minimumLimit uom="FT">2500</ns3:minimumLimit>
                                    <ns3:minimumLimitReference>MSL</ns3:minimumLimitReference>
                                    <ns3:horizontalProjection>
                                        <ns3:Surface srsName="urn:ogc:def:crs:OGC:1.3:CRS84" ns1:id="1dac8ac3-2346-4f31-b66e-773a137eb629">
                                            <ns1:patches>
                                                <ns1:PolygonPatch interpolation="planar">
                                                    <ns1:exterior>
                                                        <ns1:LinearRing>
                                                            <ns1:posList>-85.44972 40.01331 -84.8914 39.81117 -84.88686 39.77003 -84.88495 39.72875 -84.88539 39.69406 -84.88802 39.64096 -84.89403 39.58798 -84.90341 39.53525 -84.91613 39.4829 -84.93217 39.43105 -84.95148 39.37984 -84.97402 39.32939 -84.99974 39.27981 -85.02857 39.23124 -85.06044 39.18379 -85.09528 39.13758 -85.133 39.09272 -85.17351 39.04932 -85.21671 39.00749 -85.26251 38.96734 -85.31079 38.92896 -85.36143 38.89245 -85.41431 38.8579 -85.4693 38.82539 -85.52628 38.79502 -85.5851 38.76684 -85.64562 38.74095 -85.7077 38.71739 -85.77118 38.69622 -85.83592 38.67751 -85.90176 38.6613 -85.96854 38.64763 -86.0361 38.63653 -86.10427 38.62803 -86.17289 38.62215 -86.2418 38.61891 -86.2889 38.61822 -86.35791 38.61965 -86.42675 38.62373 -86.49525 38.63044 -86.56324 38.63977 -86.63057 38.65169 -86.69707 38.66618 -86.76257 38.68319 -86.82693 38.70268 -86.88999 38.72461 -86.95159 38.74892 -87.01159 38.77555 -87.06984 38.80443 -87.1262 38.83549 -87.18053 38.86865 -87.23272 38.90383 -87.28262 38.94095 -87.33012 38.9799 -87.3751 39.0206 -87.41746 39.06294 -87.4571 39.10681 -87.49391 39.15211 -87.52782 39.19873 -87.55873 39.24655 -87.58658 39.29545 -87.61129 39.34532 -87.63282 39.39603 -87.65109 39.44746 -87.66608 39.49948 -87.67774 39.55196 -87.68605 39.60478 -87.69099 39.65781 -87.69242 39.69406 -87.69194 39.74716 -87.68808 39.80014 -87.68083 39.85287 -87.67023 39.90523 -87.65629 39.95708 -87.63905 40.00831 -87.61855 40.05879 -87.59484 40.1084 -87.56798 40.15703 -87.53803 40.20455 -87.50506 40.25087 -87.46915 40.29586 -87.4304 40.33943 -87.38889 40.38146 -87.34472 40.42187 -87.298 40.46056 -87.29038 40.46652 -87.24085 40.5031 -87.18901 40.53777 -87.135 40.57045 -87.07895 40.60106 -87.02098 40.62953 -86.96125 40.6558 -86.89989 40.6798 -86.83704 40.70149 -86.77288 40.7208 -86.70753 40.7377 -86.64118 40.75214 -86.57396 40.7641 -86.50606 40.77355 -86.43762 40.78046 -86.36882 40.78481 -86.29982 40.78661 -86.2889 40.78666 -86.21942 40.78515 -86.15013 40.78106 -86.08118 40.77441 -86.01274 40.76519 -85.94499 40.75345 -85.87808 40.73919 -85.81217 40.72246 -85.74743 40.7033 -85.684 40.68174 -85.62204 40.65785 -85.56171 40.63166 -85.50314 40.60325 -85.44648 40.57268 -85.39186 40.54002 -85.33942 40.50535 -85.28927 40.46874 -85.24155 40.43028 -85.19637 40.39006 -85.15384 40.34818 -85.11405 40.30473 -85.09711 40.28475 -85.1449 40.18598 -85.47004 40.1446 -85.44972 40.01331</ns1:posList>
                                                        </ns1:LinearRing>
                                                    </ns1:exterior>
                                                    <ns1:interior>
                                                        <ns1:LinearRing>
                                                            <ns1:posList>-86.61389 40.43985 -86.61715 40.43978 -86.62041 40.43959 -86.62365 40.43928 -86.62687 40.43885 -86.63005 40.4383 -86.6332 40.43763 -86.6363 40.43684 -86.63934 40.43594 -86.64232 40.43492 -86.64524 40.4338 -86.64807 40.43257 -86.65083 40.43123 -86.65349 40.42979 -86.65606 40.42826 -86.65853 40.42663 -86.66089 40.42491 -86.66313 40.4231 -86.66526 40.42122 -86.66726 40.41925 -86.66913 40.41721 -86.67087 40.41511 -86.67247 40.41294 -86.67393 40.41072 -86.67525 40.40844 -86.67642 40.40612 -86.67743 40.40375 -86.67829 40.40135 -86.679 40.39893 -86.67955 40.39647 -86.67994 40.394 -86.68017 40.39152 -86.68024 40.38904 -86.68015 40.38655 -86.6799 40.38407 -86.67949 40.3816 -86.67892 40.37915 -86.6782 40.37672 -86.67732 40.37433 -86.67628 40.37197 -86.6751 40.36965 -86.67377 40.36738 -86.67229 40.36516 -86.67067 40.36299 -86.66892 40.3609 -86.66703 40.35886 -86.66501 40.35691 -86.66287 40.35503 -86.66061 40.35323 -86.65824 40.35152 -86.65576 40.3499 -86.65318 40.34837 -86.6505 40.34695 -86.64774 40.34562 -86.64489 40.3444 -86.64197 40.34329 -86.63898 40.34228 -86.63593 40.34139 -86.63282 40.34062 -86.62967 40.33996 -86.62648 40.33943 -86.62327 40.33901 -86.62002 40.33871 -86.61676 40.33853 -86.61389 40.33848 -86.61062 40.33855 -86.60737 40.33874 -86.60413 40.33905 -86.60091 40.33948 -86.59773 40.34003 -86.59458 40.34071 -86.59148 40.34149 -86.58844 40.3424 -86.58546 40.34341 -86.58254 40.34454 -86.57971 40.34577 -86.57695 40.34711 -86.57429 40.34855 -86.57172 40.35008 -86.56925 40.35171 -86.56689 40.35343 -86.56464 40.35524 -86.56252 40.35713 -86.56052 40.3591 -86.55864 40.36114 -86.5569 40.36324 -86.5553 40.36541 -86.55384 40.36764 -86.55252 40.36992 -86.55136 40.37224 -86.55034 40.3746 -86.54948 40.377 -86.54877 40.37943 -86.54822 40.38189 -86.54783 40.38436 -86.5476 40.38684 -86.54753 40.38933 -86.54762 40.39181 -86.54787 40.39429 -86.54828 40.39676 -86.54885 40.39921 -86.54957 40.40164 -86.55045 40.40403 -86.55148 40.40639 -86.55267 40.40871 -86.554 40.41098 -86.55548 40.4132 -86.55709 40.41536 -86.55885 40.41745 -86.56074 40.41948 -86.56275 40.42144 -86.56489 40.42332 -86.56715 40.42511 -86.56952 40.42682 -86.572 40.42844 -86.57458 40.42997 -86.57726 40.43139 -86.58002 40.43272 -86.58287 40.43394 -86.58579 40.43505 -86.58878 40.43605 -86.59183 40.43694 -86.59494 40.43771 -86.59809 40.43837 -86.60128 40.4389 -86.6045 40.43932 -86.60774 40.43962 -86.611 40.4398 -86.61389 40.43985</ns1:posList>
                                                        </ns1:LinearRing>
                                                    </ns1:interior>
                                                    <ns1:interior>
                                                        <ns1:LinearRing>
                                                            <ns1:posList>-85.92544 40.29323 -85.92248 40.29437 -85.9196 40.29562 -85.9168 40.29697 -85.91409 40.29843 -85.91148 40.29999 -85.91113 40.30021 -85.90868 40.30191 -85.90635 40.30369 -85.90413 40.30557 -85.90204 40.30752 -85.90008 40.30955 -85.89824 40.31165 -85.89655 40.31382 -85.89499 40.31604 -85.89359 40.31832 -85.89233 40.32066 -85.89122 40.32303 -85.89027 40.32545 -85.88947 40.32789 -85.88883 40.33037 -85.88835 40.33286 -85.88803 40.33537 -85.88788 40.33789 -85.88786 40.33891 -85.88794 40.3414 -85.88818 40.34388 -85.88858 40.34635 -85.88914 40.3488 -85.88985 40.35123 -85.89072 40.35362 -85.89175 40.35599 -85.89292 40.35831 -85.89425 40.36058 -85.89571 40.3628 -85.89732 40.36497 -85.89907 40.36707 -85.90095 40.3691 -85.90296 40.37106 -85.90509 40.37294 -85.90734 40.37474 -85.90971 40.37646 -85.91218 40.37808 -85.91475 40.37961 -85.91742 40.38104 -85.92018 40.38237 -85.92302 40.3836 -85.92593 40.38472 -85.92892 40.38573 -85.93196 40.38662 -85.93506 40.3874 -85.93821 40.38806 -85.94139 40.38861 -85.94461 40.38903 -85.94785 40.38934 -85.9511 40.38952 -85.95417 40.38958 -85.95743 40.38951 -85.96069 40.38932 -85.96393 40.38901 -85.96714 40.38858 -85.97032 40.38802 -85.97347 40.38735 -85.97656 40.38657 -85.9796 40.38566 -85.98258 40.38465 -85.9855 40.38353 -85.98833 40.38229 -85.99108 40.38096 -85.99375 40.37952 -85.99631 40.37798 -85.99878 40.37635 -86.00114 40.37463 -86.00338 40.37283 -86.0055 40.37094 -86.0075 40.36897 -86.00938 40.36693 -86.01111 40.36483 -86.01271 40.36266 -86.01417 40.36044 -86.01549 40.35816 -86.01665 40.35584 -86.01767 40.35347 -86.01853 40.35107 -86.01923 40.34864 -86.01978 40.34619 -86.02017 40.34372 -86.0204 40.34124 -86.02047 40.33891 -86.02041 40.33756 -86.02043 40.33622 -86.02054 40.33487 -86.02059 40.33444 -86.02019 40.33195 -86.01963 40.32948 -86.01892 40.32704 -86.01805 40.32462 -86.01702 40.32224 -86.01584 40.31991 -86.01451 40.31761 -86.01304 40.31537 -86.01142 40.31319 -86.00967 40.31107 -86.00778 40.30902 -86.00576 40.30705 -86.00362 40.30515 -86.00135 40.30333 -86.00061 40.30277 -85.99821 40.30107 -85.9957 40.29947 -85.99309 40.29796 -85.99039 40.29656 -85.9876 40.29525 -85.98473 40.29405 -85.98179 40.29296 -85.97939 40.29217 -85.97632 40.29128 -85.9732 40.2905 -85.97003 40.28984 -85.96682 40.2893 -85.96359 40.28888 -85.96032 40.28858 -85.95705 40.2884 -85.95402 40.28835 -85.95073 40.28841 -85.94745 40.2886 -85.94419 40.2889 -85.94095 40.28933 -85.93774 40.28988 -85.93457 40.29055 -85.93145 40.29133 -85.92838 40.29224 -85.92544 40.29323</ns1:posList>
                                                        </ns1:LinearRing>
                                                    </ns1:interior>
                                                    <ns1:interior>
                                                        <ns1:LinearRing>
                                                            <ns1:posList>-85.93524 40.19979 -85.9385 40.19972 -85.94175 40.19954 -85.94498 40.19923 -85.9482 40.1988 -85.95138 40.19825 -85.95452 40.19758 -85.95761 40.19679 -85.96065 40.19589 -85.96363 40.19488 -85.96654 40.19375 -85.96937 40.19252 -85.97212 40.19118 -85.97478 40.18975 -85.97735 40.18821 -85.97981 40.18658 -85.98217 40.18486 -85.98441 40.18305 -85.98654 40.18116 -85.98854 40.17919 -85.99041 40.17716 -85.99215 40.17505 -85.99375 40.17288 -85.99521 40.17065 -85.99652 40.16837 -85.99769 40.16605 -85.99871 40.16368 -85.99957 40.16128 -86.00028 40.15884 -86.00083 40.15639 -86.00122 40.15391 -86.00146 40.15143 -86.00153 40.14894 -86.00153 40.1489 -86.00145 40.14641 -86.00122 40.14392 -86.00082 40.14145 -86.00027 40.13899 -85.99956 40.13656 -85.99869 40.13416 -85.99767 40.13179 -85.9965 40.12946 -85.99519 40.12718 -85.99373 40.12496 -85.99212 40.12279 -85.99038 40.12068 -85.98851 40.11864 -85.9865 40.11667 -85.98438 40.11478 -85.98213 40.11297 -85.97977 40.11125 -85.97731 40.10962 -85.97474 40.10808 -85.97208 40.10665 -85.96933 40.10531 -85.96649 40.10408 -85.96358 40.10295 -85.9606 40.10194 -85.95756 40.10104 -85.95447 40.10026 -85.95133 40.09959 -85.94815 40.09904 -85.94494 40.09861 -85.9417 40.0983 -85.93845 40.09811 -85.93524 40.09805 -85.93198 40.09812 -85.92873 40.0983 -85.9255 40.09861 -85.92228 40.09905 -85.91911 40.0996 -85.91596 40.10027 -85.91287 40.10105 -85.90983 40.10196 -85.90685 40.10297 -85.90395 40.1041 -85.90111 40.10533 -85.89836 40.10667 -85.8957 40.10811 -85.89313 40.10964 -85.89067 40.11128 -85.88831 40.113 -85.88607 40.11481 -85.88394 40.1167 -85.88194 40.11867 -85.88007 40.12071 -85.87833 40.12282 -85.87673 40.12499 -85.87527 40.12722 -85.87396 40.1295 -85.87279 40.13183 -85.87177 40.13419 -85.87091 40.1366 -85.8702 40.13903 -85.86965 40.14149 -85.86926 40.14396 -85.86902 40.14645 -85.86895 40.1489 -85.86902 40.15139 -85.86925 40.15388 -85.86964 40.15635 -85.87019 40.15881 -85.8709 40.16124 -85.87176 40.16364 -85.87277 40.16601 -85.87394 40.16834 -85.87525 40.17062 -85.87671 40.17285 -85.87831 40.17502 -85.88004 40.17712 -85.88191 40.17916 -85.88391 40.18113 -85.88603 40.18302 -85.88828 40.18483 -85.89063 40.18655 -85.89309 40.18819 -85.89566 40.18972 -85.89832 40.19116 -85.90107 40.1925 -85.9039 40.19373 -85.90681 40.19486 -85.90979 40.19588 -85.91282 40.19678 -85.91592 40.19757 -85.91906 40.19824 -85.92224 40.19879 -85.92545 40.19922 -85.92868 40.19953 -85.93193 40.19972 -85.93519 40.19979 -85.93524 40.19979</ns1:posList>
                                                        </ns1:LinearRing>
                                                    </ns1:interior>
                                                    <ns1:interior>
                                                        <ns1:LinearRing>
                                                            <ns1:posList>-86.27004 39.90583 -86.27092 39.90334 -86.27163 39.90082 -86.27219 39.89828 -86.27258 39.89572 -86.27281 39.89314 -86.27287 39.89057 -86.27277 39.88799 -86.2725 39.88542 -86.27207 39.88286 -86.27147 39.88032 -86.27072 39.87781 -86.2698 39.87533 -86.26873 39.87288 -86.2675 39.87048 -86.26612 39.86813 -86.26459 39.86583 -86.26291 39.86359 -86.2611 39.86142 -86.25915 39.85932 -86.25706 39.8573 -86.25485 39.85535 -86.25252 39.8535 -86.25007 39.85173 -86.24751 39.85005 -86.24485 39.84848 -86.24209 39.847 -86.23924 39.84564 -86.23631 39.84438 -86.23329 39.84323 -86.23021 39.8422 -86.22707 39.84129 -86.22387 39.84049 -86.22063 39.83982 -86.21734 39.83927 -86.21403 39.83884 -86.21069 39.83854 -86.20734 39.83837 -86.20398 39.83832 -86.20062 39.8384 -86.19727 39.8386 -86.19393 39.83894 -86.19062 39.83939 -86.18735 39.83997 -86.18411 39.84068 -86.18093 39.8415 -86.1778 39.84244 -86.17474 39.8435 -86.17174 39.84468 -86.16883 39.84596 -86.166 39.84736 -86.16326 39.84886 -86.16063 39.85046 -86.15809 39.85215 -86.15567 39.85394 -86.15337 39.85582 -86.15119 39.85779 -86.14914 39.85983 -86.14722 39.86195 -86.14544 39.86414 -86.1438 39.86639 -86.14231 39.8687 -86.14096 39.87107 -86.13977 39.87348 -86.13874 39.87593 -86.13786 39.87842 -86.13714 39.88094 -86.13659 39.88349 -86.1362 39.88605 -86.13597 39.88862 -86.13591 39.8912 -86.13593 39.89224 -86.13368 39.89407 -86.13154 39.89598 -86.12953 39.89798 -86.12765 39.90004 -86.12591 39.90217 -86.1243 39.90437 -86.12284 39.90662 -86.12152 39.90893 -86.12035 39.91128 -86.11933 39.91367 -86.11847 39.9161 -86.11777 39.91856 -86.11722 39.92104 -86.11683 39.92354 -86.1166 39.92605 -86.11653 39.92857 -86.11663 39.93109 -86.11688 39.9336 -86.1173 39.93609 -86.11787 39.93857 -86.1186 39.94102 -86.11949 39.94345 -86.12053 39.94583 -86.12173 39.94818 -86.12307 39.95047 -86.12456 39.95272 -86.12619 39.9549 -86.12795 39.95702 -86.12985 39.95907 -86.13188 39.96105 -86.13404 39.96295 -86.13631 39.96476 -86.1387 39.96649 -86.14119 39.96813 -86.14379 39.96967 -86.14648 39.97111 -86.14926 39.97244 -86.15212 39.97367 -86.15506 39.9748 -86.15806 39.97581 -86.16113 39.9767 -86.16425 39.97748 -86.16742 39.97814 -86.17062 39.97868 -86.17386 39.9791 -86.17712 39.9794 -86.18039 39.97958 -86.18368 39.97963 -86.18696 39.97956 -86.19023 39.97936 -86.19348 39.97904 -86.19672 39.9786 -86.19992 39.97804 -86.20308 39.97736 -86.20619 39.97656 -86.20925 39.97565 -86.21224 39.97462 -86.21517 39.97348 -86.21802 39.97223 -86.22078 39.97088 -86.22346 39.96942 -86.22604 39.96786 -86.22852 39.96621 -86.23088 39.96447 -86.23314 39.96264 -86.23527 39.96073 -86.23728 39.95874 -86.23916 39.95668 -86.2409 39.95455 -86.24251 39.95235 -86.24397 39.9501 -86.24529 39.9478 -86.24646 39.94545 -86.24748 39.94305 -86.24834 39.94063 -86.24905 39.93817 -86.2496 39.93569 -86.24989 39.9339 -86.25285 39.93124 -86.25563 39.92847 -86.25823 39.92559 -86.26065 39.92263 -86.26287 39.91957 -86.2649 39.91644 -86.26672 39.91323 -86.26833 39.90996 -86.26974 39.90663 -86.27004 39.90583</ns1:posList>
                                                        </ns1:LinearRing>
                                                    </ns1:interior>
                                                    <ns1:interior>
                                                        <ns1:LinearRing>
                                                            <ns1:posList>-85.94131 39.75121 -85.94034 39.75357 -85.93952 39.75597 -85.93885 39.7584 -85.93834 39.76084 -85.93799 39.76331 -85.93779 39.76578 -85.93775 39.76826 -85.93787 39.77073 -85.93815 39.7732 -85.93859 39.77566 -85.93918 39.77809 -85.93992 39.7805 -85.94082 39.78288 -85.94187 39.78522 -85.94307 39.78752 -85.94442 39.78978 -85.9459 39.79197 -85.94753 39.79411 -85.94929 39.79619 -85.95118 39.7982 -85.95319 39.80013 -85.95533 39.80198 -85.95758 39.80376 -85.95994 39.80544 -85.96241 39.80703 -85.96498 39.80853 -85.96764 39.80993 -85.97038 39.81123 -85.97321 39.81242 -85.97611 39.81351 -85.97907 39.81448 -85.98209 39.81535 -85.98517 39.81609 -85.98828 39.81672 -85.99144 39.81723 -85.99462 39.81763 -85.99783 39.8179 -86.00104 39.81805 -86.00427 39.81808 -86.00749 39.81799 -86.0107 39.81777 -86.0139 39.81744 -86.01706 39.81698 -86.0202 39.81641 -86.0233 39.81572 -86.02634 39.81491 -86.02934 39.81399 -86.03227 39.81296 -86.03513 39.81182 -86.03791 39.81057 -86.04061 39.80922 -86.04323 39.80777 -86.04574 39.80622 -86.04816 39.80458 -86.05046 39.80285 -86.05266 39.80103 -86.05473 39.79914 -86.05668 39.79716 -86.0585 39.79512 -86.06019 39.79301 -86.06175 39.79084 -86.06316 39.78861 -86.06443 39.78634 -86.06555 39.78401 -86.06652 39.78165 -86.06734 39.77926 -86.06767 39.77814 -86.06875 39.77585 -86.06968 39.77352 -86.07046 39.77116 -86.07108 39.76878 -86.07156 39.76637 -86.07188 39.76395 -86.07205 39.76152 -86.07206 39.75908 -86.07191 39.75665 -86.07161 39.75423 -86.07116 39.75182 -86.07055 39.74943 -86.06979 39.74706 -86.06888 39.74473 -86.06782 39.74244 -86.06662 39.74018 -86.06528 39.73798 -86.06379 39.73583 -86.06217 39.73373 -86.06042 39.7317 -86.05854 39.72974 -86.05654 39.72785 -86.05442 39.72604 -86.05219 39.72432 -86.04985 39.72267 -86.04741 39.72112 -86.04487 39.71966 -86.04225 39.7183 -86.04081 39.71762 -86.0383 39.71638 -86.03572 39.71523 -86.03306 39.71418 -86.03034 39.71324 -86.02757 39.71239 -86.02474 39.71166 -86.02187 39.71103 -86.01897 39.7105 -86.01603 39.71009 -86.01307 39.7098 -86.0101 39.70961 -86.00712 39.70953 -86.00413 39.70957 -86.00116 39.70972 -85.99819 39.70999 -85.99525 39.71036 -85.99403 39.71055 -85.99084 39.71109 -85.98768 39.71175 -85.98458 39.71253 -85.98152 39.71342 -85.97853 39.71443 -85.9756 39.71555 -85.97275 39.71678 -85.96998 39.71811 -85.9673 39.71955 -85.96471 39.72109 -85.96223 39.72272 -85.95985 39.72444 -85.95759 39.72626 -85.95544 39.72815 -85.95342 39.73013 -85.95152 39.73217 -85.94976 39.73429 -85.94814 39.73647 -85.94665 39.73871 -85.94532 39.741 -85.94413 39.74334 -85.94309 39.74573 -85.9422 39.74814 -85.94147 39.75059 -85.94131 39.75121</ns1:posList>
                                                        </ns1:LinearRing>
                                                    </ns1:interior>
                                                    <ns1:interior>
                                                        <ns1:LinearRing>
                                                            <ns1:posList>-86.14681 39.3525 -86.15025 39.35257 -86.15367 39.35277 -86.15708 39.3531 -86.16047 39.35356 -86.16382 39.35415 -86.16713 39.35487 -86.1704 39.35571 -86.1736 39.35667 -86.17674 39.35775 -86.17981 39.35895 -86.18279 39.36027 -86.18569 39.36169 -86.1885 39.36323 -86.1912 39.36487 -86.1938 39.36661 -86.19629 39.36845 -86.19865 39.37037 -86.20089 39.37239 -86.203 39.37449 -86.20497 39.37666 -86.20681 39.37891 -86.20849 39.38123 -86.21003 39.3836 -86.21142 39.38603 -86.21265 39.38852 -86.21372 39.39104 -86.21463 39.3936 -86.21537 39.39619 -86.21595 39.39881 -86.21637 39.40145 -86.21661 39.4041 -86.21669 39.40669 -86.21662 39.40934 -86.21637 39.41199 -86.21596 39.41463 -86.21538 39.41725 -86.21464 39.41984 -86.21373 39.4224 -86.21266 39.42492 -86.21144 39.4274 -86.21005 39.42983 -86.20852 39.43221 -86.20683 39.43452 -86.205 39.43677 -86.20303 39.43894 -86.20092 39.44104 -86.19869 39.44306 -86.19632 39.44498 -86.19384 39.44682 -86.19124 39.44856 -86.18854 39.4502 -86.18574 39.45173 -86.18284 39.45316 -86.17985 39.45447 -86.17679 39.45567 -86.17365 39.45675 -86.17045 39.45772 -86.16719 39.45856 -86.16388 39.45927 -86.16053 39.45986 -86.15714 39.46032 -86.15373 39.46065 -86.1503 39.46086 -86.14687 39.46093 -86.14681 39.46093 -86.14337 39.46086 -86.13995 39.46066 -86.13654 39.46033 -86.13315 39.45987 -86.1298 39.45928 -86.12649 39.45857 -86.12323 39.45773 -86.12002 39.45677 -86.11688 39.45569 -86.11382 39.4545 -86.11083 39.45318 -86.10793 39.45176 -86.10512 39.45023 -86.10242 39.44859 -86.09982 39.44685 -86.09733 39.44502 -86.09497 39.44309 -86.09273 39.44108 -86.09062 39.43899 -86.08865 39.43681 -86.08681 39.43457 -86.08513 39.43226 -86.08359 39.42988 -86.0822 39.42745 -86.08097 39.42497 -86.0799 39.42245 -86.07899 39.41989 -86.07824 39.4173 -86.07766 39.41468 -86.07724 39.41205 -86.077 39.4094 -86.07692 39.40674 -86.07692 39.40669 -86.077 39.40403 -86.07725 39.40139 -86.07767 39.39875 -86.07825 39.39613 -86.079 39.39354 -86.07991 39.39098 -86.08099 39.38845 -86.08222 39.38597 -86.08361 39.38354 -86.08516 39.38117 -86.08685 39.37886 -86.08868 39.37661 -86.09066 39.37444 -86.09277 39.37234 -86.09501 39.37033 -86.09738 39.3684 -86.09987 39.36656 -86.10247 39.36483 -86.10518 39.36319 -86.10799 39.36166 -86.11089 39.36023 -86.11388 39.35892 -86.11695 39.35772 -86.12009 39.35664 -86.12329 39.35568 -86.12656 39.35485 -86.12987 39.35414 -86.13322 39.35355 -86.13661 39.35309 -86.14002 39.35277 -86.14345 39.35257 -86.14681 39.3525</ns1:posList>
                                                        </ns1:LinearRing>
                                                    </ns1:interior>
                                                    <ns1:interior>
                                                        <ns1:LinearRing>
                                                            <ns1:posList>-87.39128 39.19167 -87.38807 39.19174 -87.38487 39.19193 -87.38168 39.19224 -87.37851 39.19267 -87.37538 39.19323 -87.37229 39.1939 -87.36924 39.19469 -87.36625 39.19559 -87.36331 39.19661 -87.36045 39.19773 -87.35766 39.19897 -87.35495 39.2003 -87.35233 39.20174 -87.3498 39.20328 -87.34737 39.20491 -87.34505 39.20664 -87.34284 39.20844 -87.34075 39.21033 -87.33878 39.2123 -87.33694 39.21434 -87.33523 39.21645 -87.33366 39.21862 -87.33222 39.22084 -87.33093 39.22312 -87.32978 39.22545 -87.32878 39.22781 -87.32793 39.23021 -87.32724 39.23264 -87.3267 39.2351 -87.32632 39.23757 -87.32609 39.24005 -87.32602 39.24254 -87.32611 39.24502 -87.32635 39.2475 -87.32676 39.24997 -87.32732 39.25242 -87.32803 39.25485 -87.3289 39.25724 -87.32991 39.2596 -87.33108 39.26192 -87.33239 39.26419 -87.33384 39.26641 -87.33543 39.26857 -87.33716 39.27067 -87.33902 39.2727 -87.341 39.27465 -87.34311 39.27653 -87.34533 39.27833 -87.34767 39.28004 -87.3501 39.28166 -87.35264 39.28318 -87.35528 39.28461 -87.35799 39.28593 -87.3608 39.28715 -87.36367 39.28826 -87.36661 39.28926 -87.36961 39.29015 -87.37267 39.29092 -87.37576 39.29158 -87.3789 39.29212 -87.38207 39.29253 -87.38526 39.29283 -87.38846 39.29301 -87.39128 39.29306 -87.39449 39.29299 -87.39769 39.2928 -87.40088 39.29249 -87.40405 39.29206 -87.40718 39.2915 -87.41027 39.29083 -87.41332 39.29005 -87.41631 39.28915 -87.41925 39.28813 -87.42211 39.28701 -87.4249 39.28577 -87.42761 39.28444 -87.43023 39.283 -87.43276 39.28146 -87.43519 39.27983 -87.43751 39.27811 -87.43972 39.27631 -87.44181 39.27442 -87.44378 39.27245 -87.44562 39.27042 -87.44733 39.26831 -87.4489 39.26614 -87.45034 39.26392 -87.45163 39.26164 -87.45278 39.25932 -87.45378 39.25695 -87.45463 39.25455 -87.45532 39.25212 -87.45586 39.24967 -87.45624 39.2472 -87.45647 39.24472 -87.45654 39.24223 -87.45645 39.23974 -87.45621 39.23726 -87.4558 39.23479 -87.45524 39.23234 -87.45453 39.22992 -87.45366 39.22752 -87.45265 39.22516 -87.45148 39.22284 -87.45017 39.22057 -87.44872 39.21835 -87.44713 39.21618 -87.4454 39.21409 -87.44354 39.21206 -87.44156 39.2101 -87.43945 39.20822 -87.43723 39.20642 -87.43489 39.20471 -87.43246 39.20309 -87.42992 39.20156 -87.42728 39.20013 -87.42457 39.19881 -87.42176 39.19759 -87.41889 39.19648 -87.41595 39.19547 -87.41295 39.19458 -87.40989 39.19381 -87.4068 39.19315 -87.40366 39.19261 -87.40049 39.1922 -87.3973 39.1919 -87.3941 39.19172 -87.39128 39.19167</ns1:posList>
                                                        </ns1:LinearRing>
                                                    </ns1:interior>
                                                </ns1:PolygonPatch>
                                            </ns1:patches>
                                        </ns3:Surface>
                                    </ns3:horizontalProjection>
                                </ns3:AirspaceVolume>
                            </ns3:theAirspaceVolume>
                        </ns3:AirspaceGeometryComponent>
                    </ns3:geometryComponent>
                </ns3:AirspaceTimeSlice>
            </ns3:timeSlice>
        </ns3:Airspace>
    </ns8:hasMember>
    <ns8:hasMember ns2:type="simple">
        <ns3:Airspace ns1:id="19329397">
            <ns1:description ns2:type="simple">MINIMUM VECTORING ALTITUDE (MVA)</ns1:description>
            <ns1:boundedBy xsi:nil="true" xmlns:xsi="http://www.w3.org/2001/XMLSchema-instance"/>
            <ns3:timeSlice>
                <ns3:AirspaceTimeSlice>
                    <ns1:validTime ns2:type="simple">
                        <ns1:TimePeriod>
                            <ns1:beginPosition>1980-01-01T14:00:00Z</ns1:beginPosition>
                            <ns1:endPosition indeterminatePosition="unknown"/>
                        </ns1:TimePeriod>
                    </ns1:validTime>
                    <ns3:interpretation>BASELINE</ns3:interpretation>
                    <ns3:sequenceNumber>1</ns3:sequenceNumber>
                    <ns3:type>OTHER</ns3:type>
                    <ns3:designator xsi:nil="true" xmlns:xsi="http://www.w3.org/2001/XMLSchema-instance"/>
                    <ns3:localType xsi:nil="true" xmlns:xsi="http://www.w3.org/2001/XMLSchema-instance"/>
                    <ns3:name>B</ns3:name>
                    <ns3:designatorICAO xsi:nil="true" xmlns:xsi="http://www.w3.org/2001/XMLSchema-instance"/>
                    <ns3:controlType xsi:nil="true" xmlns:xsi="http://www.w3.org/2001/XMLSchema-instance"/>
                    <ns3:upperLowerSeparation xsi:nil="true" xmlns:xsi="http://www.w3.org/2001/XMLSchema-instance"/>
                    <ns3:protectedRoute xsi:nil="true" xmlns:xsi="http://www.w3.org/2001/XMLSchema-instance"/>
                    <ns3:geometryComponent>
                        <ns3:AirspaceGeometryComponent>
                            <ns3:operation xsi:nil="true" xmlns:xsi="http://www.w3.org/2001/XMLSchema-instance"/>
                            <ns3:operationSequence xsi:nil="true" xmlns:xsi="http://www.w3.org/2001/XMLSchema-instance"/>
                            <ns3:theAirspaceVolume>
                                <ns3:AirspaceVolume>
                                    <ns3:minimumLimit uom="FT">2800</ns3:minimumLimit>
                                    <ns3:minimumLimitReference>MSL</ns3:minimumLimitReference>
                                    <ns3:horizontalProjection>
                                        <ns3:Surface srsName="urn:ogc:def:crs:OGC:1.3:CRS84" ns1:id="9b91a48d-517c-452b-8481-3825714951ee">
                                            <ns1:patches>
                                                <ns1:PolygonPatch interpolation="planar">
                                                    <ns1:exterior>
                                                        <ns1:LinearRing>
                                                            <ns1:posList>-85.44972 40.01331 -84.8914 39.81117 -84.90075 39.86739 -84.91369 39.92315 -84.93018 39.97831 -84.95017 40.03274 -84.97363 40.0863 -85.0005 40.13888 -85.03071 40.19036 -85.06418 40.24059 -85.09711 40.28475 -85.1449 40.18598 -85.47004 40.1446 -85.44972 40.01331</ns1:posList>
                                                        </ns1:LinearRing>
                                                    </ns1:exterior>
                                                </ns1:PolygonPatch>
                                            </ns1:patches>
                                        </ns3:Surface>
                                    </ns3:horizontalProjection>
                                </ns3:AirspaceVolume>
                            </ns3:theAirspaceVolume>
                        </ns3:AirspaceGeometryComponent>
                    </ns3:geometryComponent>
                </ns3:AirspaceTimeSlice>
            </ns3:timeSlice>
        </ns3:Airspace>
    </ns8:hasMember>
    <ns8:hasMember ns2:type="simple">
        <ns3:Airspace ns1:id="19329392">
            <ns1:description ns2:type="simple">MINIMUM VECTORING ALTITUDE (MVA)</ns1:description>
            <ns1:boundedBy xsi:nil="true" xmlns:xsi="http://www.w3.org/2001/XMLSchema-instance"/>
            <ns3:timeSlice>
                <ns3:AirspaceTimeSlice>
                    <ns1:validTime ns2:type="simple">
                        <ns1:TimePeriod>
                            <ns1:beginPosition>1980-01-01T14:00:00Z</ns1:beginPosition>
                            <ns1:endPosition indeterminatePosition="unknown"/>
                        </ns1:TimePeriod>
                    </ns1:validTime>
                    <ns3:interpretation>BASELINE</ns3:interpretation>
                    <ns3:sequenceNumber>1</ns3:sequenceNumber>
                    <ns3:type>OTHER</ns3:type>
                    <ns3:designator xsi:nil="true" xmlns:xsi="http://www.w3.org/2001/XMLSchema-instance"/>
                    <ns3:localType xsi:nil="true" xmlns:xsi="http://www.w3.org/2001/XMLSchema-instance"/>
                    <ns3:name>C</ns3:name>
                    <ns3:designatorICAO xsi:nil="true" xmlns:xsi="http://www.w3.org/2001/XMLSchema-instance"/>
                    <ns3:controlType xsi:nil="true" xmlns:xsi="http://www.w3.org/2001/XMLSchema-instance"/>
                    <ns3:upperLowerSeparation xsi:nil="true" xmlns:xsi="http://www.w3.org/2001/XMLSchema-instance"/>
                    <ns3:protectedRoute xsi:nil="true" xmlns:xsi="http://www.w3.org/2001/XMLSchema-instance"/>
                    <ns3:geometryComponent>
                        <ns3:AirspaceGeometryComponent>
                            <ns3:operation xsi:nil="true" xmlns:xsi="http://www.w3.org/2001/XMLSchema-instance"/>
                            <ns3:operationSequence xsi:nil="true" xmlns:xsi="http://www.w3.org/2001/XMLSchema-instance"/>
                            <ns3:theAirspaceVolume>
                                <ns3:AirspaceVolume>
                                    <ns3:minimumLimit uom="FT">2900</ns3:minimumLimit>
                                    <ns3:minimumLimitReference>MSL</ns3:minimumLimitReference>
                                    <ns3:horizontalProjection>
                                        <ns3:Surface srsName="urn:ogc:def:crs:OGC:1.3:CRS84" ns1:id="9c32cca9-851b-4c71-a495-eae9e2206980">
                                            <ns1:patches>
                                                <ns1:PolygonPatch interpolation="planar">
                                                    <ns1:exterior>
                                                        <ns1:LinearRing>
                                                            <ns1:posList>-86.27004 39.90583 -86.27092 39.90334 -86.27163 39.90082 -86.27219 39.89828 -86.27258 39.89572 -86.27281 39.89314 -86.27287 39.89057 -86.27277 39.88799 -86.2725 39.88542 -86.27207 39.88286 -86.27147 39.88032 -86.27072 39.87781 -86.2698 39.87533 -86.26873 39.87288 -86.2675 39.87048 -86.26612 39.86813 -86.26459 39.86583 -86.26291 39.86359 -86.2611 39.86142 -86.25915 39.85932 -86.25706 39.8573 -86.25485 39.85535 -86.25252 39.8535 -86.25007 39.85173 -86.24751 39.85005 -86.24485 39.84848 -86.24209 39.847 -86.23924 39.84564 -86.23631 39.84438 -86.23329 39.84323 -86.23021 39.8422 -86.22707 39.84129 -86.22387 39.84049 -86.22063 39.83982 -86.21734 39.83927 -86.21403 39.83884 -86.21069 39.83854 -86.20734 39.83837 -86.20398 39.83832 -86.20062 39.8384 -86.19727 39.8386 -86.19393 39.83894 -86.19062 39.83939 -86.18735 39.83997 -86.18411 39.84068 -86.18093 39.8415 -86.1778 39.84244 -86.17474 39.8435 -86.17174 39.84468 -86.16883 39.84596 -86.166 39.84736 -86.16326 39.84886 -86.16063 39.85046 -86.15809 39.85215 -86.15567 39.85394 -86.15337 39.85582 -86.15119 39.85779 -86.14914 39.85983 -86.14722 39.86195 -86.14544 39.86414 -86.1438 39.86639 -86.14231 39.8687 -86.14096 39.87107 -86.13977 39.87348 -86.13874 39.87593 -86.13786 39.87842 -86.13714 39.88094 -86.13659 39.88349 -86.1362 39.88605 -86.13597 39.88862 -86.13591 39.8912 -86.13593 39.89224 -86.13368 39.89407 -86.13154 39.89598 -86.12953 39.89798 -86.12765 39.90004 -86.12591 39.90217 -86.1243 39.90437 -86.12284 39.90662 -86.12152 39.90893 -86.12035 39.91128 -86.11933 39.91367 -86.11847 39.9161 -86.11777 39.91856 -86.11722 39.92104 -86.11683 39.92354 -86.1166 39.92605 -86.11653 39.92857 -86.11663 39.93109 -86.11688 39.9336 -86.1173 39.93609 -86.11787 39.93857 -86.1186 39.94102 -86.11949 39.94345 -86.12053 39.94583 -86.12173 39.94818 -86.12307 39.95047 -86.12456 39.95272 -86.12619 39.9549 -86.12795 39.95702 -86.12985 39.95907 -86.13188 39.96105 -86.13404 39.96295 -86.13631 39.96476 -86.1387 39.96649 -86.14119 39.96813 -86.14379 39.96967 -86.14648 39.97111 -86.14926 39.97244 -86.15212 39.97367 -86.15506 39.9748 -86.15806 39.97581 -86.16113 39.9767 -86.16425 39.97748 -86.16742 39.97814 -86.17062 39.97868 -86.17386 39.9791 -86.17712 39.9794 -86.18039 39.97958 -86.18368 39.97963 -86.18696 39.97956 -86.19023 39.97936 -86.19348 39.97904 -86.19672 39.9786 -86.19992 39.97804 -86.20308 39.97736 -86.20619 39.97656 -86.20925 39.97565 -86.21224 39.97462 -86.21517 39.97348 -86.21802 39.97223 -86.22078 39.97088 -86.22346 39.96942 -86.22604 39.96786 -86.22852 39.96621 -86.23088 39.96447 -86.23314 39.96264 -86.23527 39.96073 -86.23728 39.95874 -86.23916 39.95668 -86.2409 39.95455 -86.24251 39.95235 -86.24397 39.9501 -86.24529 39.9478 -86.24646 39.94545 -86.24748 39.94305 -86.24834 39.94063 -86.24905 39.93817 -86.2496 39.93569 -86.24989 39.9339 -86.25285 39.93124 -86.25563 39.92847 -86.25823 39.92559 -86.26065 39.92263 -86.26287 39.91957 -86.2649 39.91644 -86.26672 39.91323 -86.26833 39.90996 -86.26974 39.90663 -86.27004 39.90583</ns1:posList>
                                                        </ns1:LinearRing>
                                                    </ns1:exterior>
                                                </ns1:PolygonPatch>
                                            </ns1:patches>
                                        </ns3:Surface>
                                    </ns3:horizontalProjection>
                                </ns3:AirspaceVolume>
                            </ns3:theAirspaceVolume>
                        </ns3:AirspaceGeometryComponent>
                    </ns3:geometryComponent>
                </ns3:AirspaceTimeSlice>
            </ns3:timeSlice>
        </ns3:Airspace>
    </ns8:hasMember>
    <ns8:hasMember ns2:type="simple">
        <ns3:Airspace ns1:id="19329393">
            <ns1:description ns2:type="simple">MINIMUM VECTORING ALTITUDE (MVA)</ns1:description>
            <ns1:boundedBy xsi:nil="true" xmlns:xsi="http://www.w3.org/2001/XMLSchema-instance"/>
            <ns3:timeSlice>
                <ns3:AirspaceTimeSlice>
                    <ns1:validTime ns2:type="simple">
                        <ns1:TimePeriod>
                            <ns1:beginPosition>1980-01-01T14:00:00Z</ns1:beginPosition>
                            <ns1:endPosition indeterminatePosition="unknown"/>
                        </ns1:TimePeriod>
                    </ns1:validTime>
                    <ns3:interpretation>BASELINE</ns3:interpretation>
                    <ns3:sequenceNumber>1</ns3:sequenceNumber>
                    <ns3:type>OTHER</ns3:type>
                    <ns3:designator xsi:nil="true" xmlns:xsi="http://www.w3.org/2001/XMLSchema-instance"/>
                    <ns3:localType xsi:nil="true" xmlns:xsi="http://www.w3.org/2001/XMLSchema-instance"/>
                    <ns3:name>D</ns3:name>
                    <ns3:designatorICAO xsi:nil="true" xmlns:xsi="http://www.w3.org/2001/XMLSchema-instance"/>
                    <ns3:controlType xsi:nil="true" xmlns:xsi="http://www.w3.org/2001/XMLSchema-instance"/>
                    <ns3:upperLowerSeparation xsi:nil="true" xmlns:xsi="http://www.w3.org/2001/XMLSchema-instance"/>
                    <ns3:protectedRoute xsi:nil="true" xmlns:xsi="http://www.w3.org/2001/XMLSchema-instance"/>
                    <ns3:geometryComponent>
                        <ns3:AirspaceGeometryComponent>
                            <ns3:operation xsi:nil="true" xmlns:xsi="http://www.w3.org/2001/XMLSchema-instance"/>
                            <ns3:operationSequence xsi:nil="true" xmlns:xsi="http://www.w3.org/2001/XMLSchema-instance"/>
                            <ns3:theAirspaceVolume>
                                <ns3:AirspaceVolume>
                                    <ns3:minimumLimit uom="FT">2800</ns3:minimumLimit>
                                    <ns3:minimumLimitReference>MSL</ns3:minimumLimitReference>
                                    <ns3:horizontalProjection>
                                        <ns3:Surface srsName="urn:ogc:def:crs:OGC:1.3:CRS84" ns1:id="4315e528-fcab-4f84-acc5-a1c431c0b1eb">
                                            <ns1:patches>
                                                <ns1:PolygonPatch interpolation="planar">
                                                    <ns1:exterior>
                                                        <ns1:LinearRing>
                                                            <ns1:posList>-85.93524 40.19979 -85.9385 40.19972 -85.94175 40.19954 -85.94498 40.19923 -85.9482 40.1988 -85.95138 40.19825 -85.95452 40.19758 -85.95761 40.19679 -85.96065 40.19589 -85.96363 40.19488 -85.96654 40.19375 -85.96937 40.19252 -85.97212 40.19118 -85.97478 40.18975 -85.97735 40.18821 -85.97981 40.18658 -85.98217 40.18486 -85.98441 40.18305 -85.98654 40.18116 -85.98854 40.17919 -85.99041 40.17716 -85.99215 40.17505 -85.99375 40.17288 -85.99521 40.17065 -85.99652 40.16837 -85.99769 40.16605 -85.99871 40.16368 -85.99957 40.16128 -86.00028 40.15884 -86.00083 40.15639 -86.00122 40.15391 -86.00146 40.15143 -86.00153 40.14894 -86.00153 40.1489 -86.00145 40.14641 -86.00122 40.14392 -86.00082 40.14145 -86.00027 40.13899 -85.99956 40.13656 -85.99869 40.13416 -85.99767 40.13179 -85.9965 40.12946 -85.99519 40.12718 -85.99373 40.12496 -85.99212 40.12279 -85.99038 40.12068 -85.98851 40.11864 -85.9865 40.11667 -85.98438 40.11478 -85.98213 40.11297 -85.97977 40.11125 -85.97731 40.10962 -85.97474 40.10808 -85.97208 40.10665 -85.96933 40.10531 -85.96649 40.10408 -85.96358 40.10295 -85.9606 40.10194 -85.95756 40.10104 -85.95447 40.10026 -85.95133 40.09959 -85.94815 40.09904 -85.94494 40.09861 -85.9417 40.0983 -85.93845 40.09811 -85.93524 40.09805 -85.93198 40.09812 -85.92873 40.0983 -85.9255 40.09861 -85.92228 40.09905 -85.91911 40.0996 -85.91596 40.10027 -85.91287 40.10105 -85.90983 40.10196 -85.90685 40.10297 -85.90395 40.1041 -85.90111 40.10533 -85.89836 40.10667 -85.8957 40.10811 -85.89313 40.10964 -85.89067 40.11128 -85.88831 40.113 -85.88607 40.11481 -85.88394 40.1167 -85.88194 40.11867 -85.88007 40.12071 -85.87833 40.12282 -85.87673 40.12499 -85.87527 40.12722 -85.87396 40.1295 -85.87279 40.13183 -85.87177 40.13419 -85.87091 40.1366 -85.8702 40.13903 -85.86965 40.14149 -85.86926 40.14396 -85.86902 40.14645 -85.86895 40.1489 -85.86902 40.15139 -85.86925 40.15388 -85.86964 40.15635 -85.87019 40.15881 -85.8709 40.16124 -85.87176 40.16364 -85.87277 40.16601 -85.87394 40.16834 -85.87525 40.17062 -85.87671 40.17285 -85.87831 40.17502 -85.88004 40.17712 -85.88191 40.17916 -85.88391 40.18113 -85.88603 40.18302 -85.88828 40.18483 -85.89063 40.18655 -85.89309 40.18819 -85.89566 40.18972 -85.89832 40.19116 -85.90107 40.1925 -85.9039 40.19373 -85.90681 40.19486 -85.90979 40.19588 -85.91282 40.19678 -85.91592 40.19757 -85.91906 40.19824 -85.92224 40.19879 -85.92545 40.19922 -85.92868 40.19953 -85.93193 40.19972 -85.93519 40.19979 -85.93524 40.19979</ns1:posList>
                                                        </ns1:LinearRing>
                                                    </ns1:exterior>
                                                </ns1:PolygonPatch>
                                            </ns1:patches>
                                        </ns3:Surface>
                                    </ns3:horizontalProjection>
                                </ns3:AirspaceVolume>
                            </ns3:theAirspaceVolume>
                        </ns3:AirspaceGeometryComponent>
                    </ns3:geometryComponent>
                </ns3:AirspaceTimeSlice>
            </ns3:timeSlice>
        </ns3:Airspace>
    </ns8:hasMember>
    <ns8:hasMember ns2:type="simple">
        <ns3:Airspace ns1:id="19329391">
            <ns1:description ns2:type="simple">MINIMUM VECTORING ALTITUDE (MVA)</ns1:description>
            <ns1:boundedBy xsi:nil="true" xmlns:xsi="http://www.w3.org/2001/XMLSchema-instance"/>
            <ns3:timeSlice>
                <ns3:AirspaceTimeSlice>
                    <ns1:validTime ns2:type="simple">
                        <ns1:TimePeriod>
                            <ns1:beginPosition>1980-01-01T14:00:00Z</ns1:beginPosition>
                            <ns1:endPosition indeterminatePosition="unknown"/>
                        </ns1:TimePeriod>
                    </ns1:validTime>
                    <ns3:interpretation>BASELINE</ns3:interpretation>
                    <ns3:sequenceNumber>1</ns3:sequenceNumber>
                    <ns3:type>OTHER</ns3:type>
                    <ns3:designator xsi:nil="true" xmlns:xsi="http://www.w3.org/2001/XMLSchema-instance"/>
                    <ns3:localType xsi:nil="true" xmlns:xsi="http://www.w3.org/2001/XMLSchema-instance"/>
                    <ns3:name>E</ns3:name>
                    <ns3:designatorICAO xsi:nil="true" xmlns:xsi="http://www.w3.org/2001/XMLSchema-instance"/>
                    <ns3:controlType xsi:nil="true" xmlns:xsi="http://www.w3.org/2001/XMLSchema-instance"/>
                    <ns3:upperLowerSeparation xsi:nil="true" xmlns:xsi="http://www.w3.org/2001/XMLSchema-instance"/>
                    <ns3:protectedRoute xsi:nil="true" xmlns:xsi="http://www.w3.org/2001/XMLSchema-instance"/>
                    <ns3:geometryComponent>
                        <ns3:AirspaceGeometryComponent>
                            <ns3:operation xsi:nil="true" xmlns:xsi="http://www.w3.org/2001/XMLSchema-instance"/>
                            <ns3:operationSequence xsi:nil="true" xmlns:xsi="http://www.w3.org/2001/XMLSchema-instance"/>
                            <ns3:theAirspaceVolume>
                                <ns3:AirspaceVolume>
                                    <ns3:minimumLimit uom="FT">2900</ns3:minimumLimit>
                                    <ns3:minimumLimitReference>MSL</ns3:minimumLimitReference>
                                    <ns3:horizontalProjection>
                                        <ns3:Surface srsName="urn:ogc:def:crs:OGC:1.3:CRS84" ns1:id="92aa3e03-f581-47d1-8eb8-52614e71b635">
                                            <ns1:patches>
                                                <ns1:PolygonPatch interpolation="planar">
                                                    <ns1:exterior>
                                                        <ns1:LinearRing>
                                                            <ns1:posList>-85.94131 39.75121 -85.94034 39.75357 -85.93952 39.75597 -85.93885 39.7584 -85.93834 39.76084 -85.93799 39.76331 -85.93779 39.76578 -85.93775 39.76826 -85.93787 39.77073 -85.93815 39.7732 -85.93859 39.77566 -85.93918 39.77809 -85.93992 39.7805 -85.94082 39.78288 -85.94187 39.78522 -85.94307 39.78752 -85.94442 39.78978 -85.9459 39.79197 -85.94753 39.79411 -85.94929 39.79619 -85.95118 39.7982 -85.95319 39.80013 -85.95533 39.80198 -85.95758 39.80376 -85.95994 39.80544 -85.96241 39.80703 -85.96498 39.80853 -85.96764 39.80993 -85.97038 39.81123 -85.97321 39.81242 -85.97611 39.81351 -85.97907 39.81448 -85.98209 39.81535 -85.98517 39.81609 -85.98828 39.81672 -85.99144 39.81723 -85.99462 39.81763 -85.99783 39.8179 -86.00104 39.81805 -86.00427 39.81808 -86.00749 39.81799 -86.0107 39.81777 -86.0139 39.81744 -86.01706 39.81698 -86.0202 39.81641 -86.0233 39.81572 -86.02634 39.81491 -86.02934 39.81399 -86.03227 39.81296 -86.03513 39.81182 -86.03791 39.81057 -86.04061 39.80922 -86.04323 39.80777 -86.04574 39.80622 -86.04816 39.80458 -86.05046 39.80285 -86.05266 39.80103 -86.05473 39.79914 -86.05668 39.79716 -86.0585 39.79512 -86.06019 39.79301 -86.06175 39.79084 -86.06316 39.78861 -86.06443 39.78634 -86.06555 39.78401 -86.06652 39.78165 -86.06734 39.77926 -86.06767 39.77814 -86.06875 39.77585 -86.06968 39.77352 -86.07046 39.77116 -86.07108 39.76878 -86.07156 39.76637 -86.07188 39.76395 -86.07205 39.76152 -86.07206 39.75908 -86.07191 39.75665 -86.07161 39.75423 -86.07116 39.75182 -86.07055 39.74943 -86.06979 39.74706 -86.06888 39.74473 -86.06782 39.74244 -86.06662 39.74018 -86.06528 39.73798 -86.06379 39.73583 -86.06217 39.73373 -86.06042 39.7317 -86.05854 39.72974 -86.05654 39.72785 -86.05442 39.72604 -86.05219 39.72432 -86.04985 39.72267 -86.04741 39.72112 -86.04487 39.71966 -86.04225 39.7183 -86.04081 39.71762 -86.0383 39.71638 -86.03572 39.71523 -86.03306 39.71418 -86.03034 39.71324 -86.02757 39.71239 -86.02474 39.71166 -86.02187 39.71103 -86.01897 39.7105 -86.01603 39.71009 -86.01307 39.7098 -86.0101 39.70961 -86.00712 39.70953 -86.00413 39.70957 -86.00116 39.70972 -85.99819 39.70999 -85.99525 39.71036 -85.99403 39.71055 -85.99084 39.71109 -85.98768 39.71175 -85.98458 39.71253 -85.98152 39.71342 -85.97853 39.71443 -85.9756 39.71555 -85.97275 39.71678 -85.96998 39.71811 -85.9673 39.71955 -85.96471 39.72109 -85.96223 39.72272 -85.95985 39.72444 -85.95759 39.72626 -85.95544 39.72815 -85.95342 39.73013 -85.95152 39.73217 -85.94976 39.73429 -85.94814 39.73647 -85.94665 39.73871 -85.94532 39.741 -85.94413 39.74334 -85.94309 39.74573 -85.9422 39.74814 -85.94147 39.75059 -85.94131 39.75121</ns1:posList>
                                                        </ns1:LinearRing>
                                                    </ns1:exterior>
                                                </ns1:PolygonPatch>
                                            </ns1:patches>
                                        </ns3:Surface>
                                    </ns3:horizontalProjection>
                                </ns3:AirspaceVolume>
                            </ns3:theAirspaceVolume>
                        </ns3:AirspaceGeometryComponent>
                    </ns3:geometryComponent>
                </ns3:AirspaceTimeSlice>
            </ns3:timeSlice>
        </ns3:Airspace>
    </ns8:hasMember>
    <ns8:hasMember ns2:type="simple">
        <ns3:Airspace ns1:id="19329390">
            <ns1:description ns2:type="simple">MINIMUM VECTORING ALTITUDE (MVA)</ns1:description>
            <ns1:boundedBy xsi:nil="true" xmlns:xsi="http://www.w3.org/2001/XMLSchema-instance"/>
            <ns3:timeSlice>
                <ns3:AirspaceTimeSlice>
                    <ns1:validTime ns2:type="simple">
                        <ns1:TimePeriod>
                            <ns1:beginPosition>1980-01-01T14:00:00Z</ns1:beginPosition>
                            <ns1:endPosition indeterminatePosition="unknown"/>
                        </ns1:TimePeriod>
                    </ns1:validTime>
                    <ns3:interpretation>BASELINE</ns3:interpretation>
                    <ns3:sequenceNumber>1</ns3:sequenceNumber>
                    <ns3:type>OTHER</ns3:type>
                    <ns3:designator xsi:nil="true" xmlns:xsi="http://www.w3.org/2001/XMLSchema-instance"/>
                    <ns3:localType xsi:nil="true" xmlns:xsi="http://www.w3.org/2001/XMLSchema-instance"/>
                    <ns3:name>F</ns3:name>
                    <ns3:designatorICAO xsi:nil="true" xmlns:xsi="http://www.w3.org/2001/XMLSchema-instance"/>
                    <ns3:controlType xsi:nil="true" xmlns:xsi="http://www.w3.org/2001/XMLSchema-instance"/>
                    <ns3:upperLowerSeparation xsi:nil="true" xmlns:xsi="http://www.w3.org/2001/XMLSchema-instance"/>
                    <ns3:protectedRoute xsi:nil="true" xmlns:xsi="http://www.w3.org/2001/XMLSchema-instance"/>
                    <ns3:geometryComponent>
                        <ns3:AirspaceGeometryComponent>
                            <ns3:operation xsi:nil="true" xmlns:xsi="http://www.w3.org/2001/XMLSchema-instance"/>
                            <ns3:operationSequence xsi:nil="true" xmlns:xsi="http://www.w3.org/2001/XMLSchema-instance"/>
                            <ns3:theAirspaceVolume>
                                <ns3:AirspaceVolume>
                                    <ns3:minimumLimit uom="FT">3000</ns3:minimumLimit>
                                    <ns3:minimumLimitReference>MSL</ns3:minimumLimitReference>
                                    <ns3:horizontalProjection>
                                        <ns3:Surface srsName="urn:ogc:def:crs:OGC:1.3:CRS84" ns1:id="f81a5482-0aa0-48bd-a8f1-f33ce195bff4">
                                            <ns1:patches>
                                                <ns1:PolygonPatch interpolation="planar">
                                                    <ns1:exterior>
                                                        <ns1:LinearRing>
                                                            <ns1:posList>-86.14681 39.3525 -86.15025 39.35257 -86.15367 39.35277 -86.15708 39.3531 -86.16047 39.35356 -86.16382 39.35415 -86.16713 39.35487 -86.1704 39.35571 -86.1736 39.35667 -86.17674 39.35775 -86.17981 39.35895 -86.18279 39.36027 -86.18569 39.36169 -86.1885 39.36323 -86.1912 39.36487 -86.1938 39.36661 -86.19629 39.36845 -86.19865 39.37037 -86.20089 39.37239 -86.203 39.37449 -86.20497 39.37666 -86.20681 39.37891 -86.20849 39.38123 -86.21003 39.3836 -86.21142 39.38603 -86.21265 39.38852 -86.21372 39.39104 -86.21463 39.3936 -86.21537 39.39619 -86.21595 39.39881 -86.21637 39.40145 -86.21661 39.4041 -86.21669 39.40669 -86.21662 39.40934 -86.21637 39.41199 -86.21596 39.41463 -86.21538 39.41725 -86.21464 39.41984 -86.21373 39.4224 -86.21266 39.42492 -86.21144 39.4274 -86.21005 39.42983 -86.20852 39.43221 -86.20683 39.43452 -86.205 39.43677 -86.20303 39.43894 -86.20092 39.44104 -86.19869 39.44306 -86.19632 39.44498 -86.19384 39.44682 -86.19124 39.44856 -86.18854 39.4502 -86.18574 39.45173 -86.18284 39.45316 -86.17985 39.45447 -86.17679 39.45567 -86.17365 39.45675 -86.17045 39.45772 -86.16719 39.45856 -86.16388 39.45927 -86.16053 39.45986 -86.15714 39.46032 -86.15373 39.46065 -86.1503 39.46086 -86.14687 39.46093 -86.14681 39.46093 -86.14337 39.46086 -86.13995 39.46066 -86.13654 39.46033 -86.13315 39.45987 -86.1298 39.45928 -86.12649 39.45857 -86.12323 39.45773 -86.12002 39.45677 -86.11688 39.45569 -86.11382 39.4545 -86.11083 39.45318 -86.10793 39.45176 -86.10512 39.45023 -86.10242 39.44859 -86.09982 39.44685 -86.09733 39.44502 -86.09497 39.44309 -86.09273 39.44108 -86.09062 39.43899 -86.08865 39.43681 -86.08681 39.43457 -86.08513 39.43226 -86.08359 39.42988 -86.0822 39.42745 -86.08097 39.42497 -86.0799 39.42245 -86.07899 39.41989 -86.07824 39.4173 -86.07766 39.41468 -86.07724 39.41205 -86.077 39.4094 -86.07692 39.40674 -86.07692 39.40669 -86.077 39.40403 -86.07725 39.40139 -86.07767 39.39875 -86.07825 39.39613 -86.079 39.39354 -86.07991 39.39098 -86.08099 39.38845 -86.08222 39.38597 -86.08361 39.38354 -86.08516 39.38117 -86.08685 39.37886 -86.08868 39.37661 -86.09066 39.37444 -86.09277 39.37234 -86.09501 39.37033 -86.09738 39.3684 -86.09987 39.36656 -86.10247 39.36483 -86.10518 39.36319 -86.10799 39.36166 -86.11089 39.36023 -86.11388 39.35892 -86.11695 39.35772 -86.12009 39.35664 -86.12329 39.35568 -86.12656 39.35485 -86.12987 39.35414 -86.13322 39.35355 -86.13661 39.35309 -86.14002 39.35277 -86.14345 39.35257 -86.14681 39.3525</ns1:posList>
                                                        </ns1:LinearRing>
                                                    </ns1:exterior>
                                                </ns1:PolygonPatch>
                                            </ns1:patches>
                                        </ns3:Surface>
                                    </ns3:horizontalProjection>
                                </ns3:AirspaceVolume>
                            </ns3:theAirspaceVolume>
                        </ns3:AirspaceGeometryComponent>
                    </ns3:geometryComponent>
                </ns3:AirspaceTimeSlice>
            </ns3:timeSlice>
        </ns3:Airspace>
    </ns8:hasMember>
    <ns8:hasMember ns2:type="simple">
        <ns3:Airspace ns1:id="19329394">
            <ns1:description ns2:type="simple">MINIMUM VECTORING ALTITUDE (MVA)</ns1:description>
            <ns1:boundedBy xsi:nil="true" xmlns:xsi="http://www.w3.org/2001/XMLSchema-instance"/>
            <ns3:timeSlice>
                <ns3:AirspaceTimeSlice>
                    <ns1:validTime ns2:type="simple">
                        <ns1:TimePeriod>
                            <ns1:beginPosition>1980-01-01T14:00:00Z</ns1:beginPosition>
                            <ns1:endPosition indeterminatePosition="unknown"/>
                        </ns1:TimePeriod>
                    </ns1:validTime>
                    <ns3:interpretation>BASELINE</ns3:interpretation>
                    <ns3:sequenceNumber>1</ns3:sequenceNumber>
                    <ns3:type>OTHER</ns3:type>
                    <ns3:designator xsi:nil="true" xmlns:xsi="http://www.w3.org/2001/XMLSchema-instance"/>
                    <ns3:localType xsi:nil="true" xmlns:xsi="http://www.w3.org/2001/XMLSchema-instance"/>
                    <ns3:name>G</ns3:name>
                    <ns3:designatorICAO xsi:nil="true" xmlns:xsi="http://www.w3.org/2001/XMLSchema-instance"/>
                    <ns3:controlType xsi:nil="true" xmlns:xsi="http://www.w3.org/2001/XMLSchema-instance"/>
                    <ns3:upperLowerSeparation xsi:nil="true" xmlns:xsi="http://www.w3.org/2001/XMLSchema-instance"/>
                    <ns3:protectedRoute xsi:nil="true" xmlns:xsi="http://www.w3.org/2001/XMLSchema-instance"/>
                    <ns3:geometryComponent>
                        <ns3:AirspaceGeometryComponent>
                            <ns3:operation xsi:nil="true" xmlns:xsi="http://www.w3.org/2001/XMLSchema-instance"/>
                            <ns3:operationSequence xsi:nil="true" xmlns:xsi="http://www.w3.org/2001/XMLSchema-instance"/>
                            <ns3:theAirspaceVolume>
                                <ns3:AirspaceVolume>
                                    <ns3:minimumLimit uom="FT">2600</ns3:minimumLimit>
                                    <ns3:minimumLimitReference>MSL</ns3:minimumLimitReference>
                                    <ns3:horizontalProjection>
                                        <ns3:Surface srsName="urn:ogc:def:crs:OGC:1.3:CRS84" ns1:id="9013261d-6408-4906-8cf3-462a5f71f4e9">
                                            <ns1:patches>
                                                <ns1:PolygonPatch interpolation="planar">
                                                    <ns1:exterior>
                                                        <ns1:LinearRing>
                                                            <ns1:posList>-85.92544 40.29323 -85.92248 40.29437 -85.9196 40.29562 -85.9168 40.29697 -85.91409 40.29843 -85.91148 40.29999 -85.91113 40.30021 -85.90868 40.30191 -85.90635 40.30369 -85.90413 40.30557 -85.90204 40.30752 -85.90008 40.30955 -85.89824 40.31165 -85.89655 40.31382 -85.89499 40.31604 -85.89359 40.31832 -85.89233 40.32066 -85.89122 40.32303 -85.89027 40.32545 -85.88947 40.32789 -85.88883 40.33037 -85.88835 40.33286 -85.88803 40.33537 -85.88788 40.33789 -85.88786 40.33891 -85.88794 40.3414 -85.88818 40.34388 -85.88858 40.34635 -85.88914 40.3488 -85.88985 40.35123 -85.89072 40.35362 -85.89175 40.35599 -85.89292 40.35831 -85.89425 40.36058 -85.89571 40.3628 -85.89732 40.36497 -85.89907 40.36707 -85.90095 40.3691 -85.90296 40.37106 -85.90509 40.37294 -85.90734 40.37474 -85.90971 40.37646 -85.91218 40.37808 -85.91475 40.37961 -85.91742 40.38104 -85.92018 40.38237 -85.92302 40.3836 -85.92593 40.38472 -85.92892 40.38573 -85.93196 40.38662 -85.93506 40.3874 -85.93821 40.38806 -85.94139 40.38861 -85.94461 40.38903 -85.94785 40.38934 -85.9511 40.38952 -85.95417 40.38958 -85.95743 40.38951 -85.96069 40.38932 -85.96393 40.38901 -85.96714 40.38858 -85.97032 40.38802 -85.97347 40.38735 -85.97656 40.38657 -85.9796 40.38566 -85.98258 40.38465 -85.9855 40.38353 -85.98833 40.38229 -85.99108 40.38096 -85.99375 40.37952 -85.99631 40.37798 -85.99878 40.37635 -86.00114 40.37463 -86.00338 40.37283 -86.0055 40.37094 -86.0075 40.36897 -86.00938 40.36693 -86.01111 40.36483 -86.01271 40.36266 -86.01417 40.36044 -86.01549 40.35816 -86.01665 40.35584 -86.01767 40.35347 -86.01853 40.35107 -86.01923 40.34864 -86.01978 40.34619 -86.02017 40.34372 -86.0204 40.34124 -86.02047 40.33891 -86.02041 40.33756 -86.02043 40.33622 -86.02054 40.33487 -86.02059 40.33444 -86.02019 40.33195 -86.01963 40.32948 -86.01892 40.32704 -86.01805 40.32462 -86.01702 40.32224 -86.01584 40.31991 -86.01451 40.31761 -86.01304 40.31537 -86.01142 40.31319 -86.00967 40.31107 -86.00778 40.30902 -86.00576 40.30705 -86.00362 40.30515 -86.00135 40.30333 -86.00061 40.30277 -85.99821 40.30107 -85.9957 40.29947 -85.99309 40.29796 -85.99039 40.29656 -85.9876 40.29525 -85.98473 40.29405 -85.98179 40.29296 -85.97939 40.29217 -85.97632 40.29128 -85.9732 40.2905 -85.97003 40.28984 -85.96682 40.2893 -85.96359 40.28888 -85.96032 40.28858 -85.95705 40.2884 -85.95402 40.28835 -85.95073 40.28841 -85.94745 40.2886 -85.94419 40.2889 -85.94095 40.28933 -85.93774 40.28988 -85.93457 40.29055 -85.93145 40.29133 -85.92838 40.29224 -85.92544 40.29323</ns1:posList>
                                                        </ns1:LinearRing>
                                                    </ns1:exterior>
                                                </ns1:PolygonPatch>
                                            </ns1:patches>
                                        </ns3:Surface>
                                    </ns3:horizontalProjection>
                                </ns3:AirspaceVolume>
                            </ns3:theAirspaceVolume>
                        </ns3:AirspaceGeometryComponent>
                    </ns3:geometryComponent>
                </ns3:AirspaceTimeSlice>
            </ns3:timeSlice>
        </ns3:Airspace>
    </ns8:hasMember>
    <ns8:hasMember ns2:type="simple">
        <ns3:Airspace ns1:id="19329396">
            <ns1:description ns2:type="simple">MINIMUM VECTORING ALTITUDE (MVA)</ns1:description>
            <ns1:boundedBy xsi:nil="true" xmlns:xsi="http://www.w3.org/2001/XMLSchema-instance"/>
            <ns3:timeSlice>
                <ns3:AirspaceTimeSlice>
                    <ns1:validTime ns2:type="simple">
                        <ns1:TimePeriod>
                            <ns1:beginPosition>1980-01-01T14:00:00Z</ns1:beginPosition>
                            <ns1:endPosition indeterminatePosition="unknown"/>
                        </ns1:TimePeriod>
                    </ns1:validTime>
                    <ns3:interpretation>BASELINE</ns3:interpretation>
                    <ns3:sequenceNumber>1</ns3:sequenceNumber>
                    <ns3:type>OTHER</ns3:type>
                    <ns3:designator xsi:nil="true" xmlns:xsi="http://www.w3.org/2001/XMLSchema-instance"/>
                    <ns3:localType xsi:nil="true" xmlns:xsi="http://www.w3.org/2001/XMLSchema-instance"/>
                    <ns3:name>H</ns3:name>
                    <ns3:designatorICAO xsi:nil="true" xmlns:xsi="http://www.w3.org/2001/XMLSchema-instance"/>
                    <ns3:controlType xsi:nil="true" xmlns:xsi="http://www.w3.org/2001/XMLSchema-instance"/>
                    <ns3:upperLowerSeparation xsi:nil="true" xmlns:xsi="http://www.w3.org/2001/XMLSchema-instance"/>
                    <ns3:protectedRoute xsi:nil="true" xmlns:xsi="http://www.w3.org/2001/XMLSchema-instance"/>
                    <ns3:geometryComponent>
                        <ns3:AirspaceGeometryComponent>
                            <ns3:operation xsi:nil="true" xmlns:xsi="http://www.w3.org/2001/XMLSchema-instance"/>
                            <ns3:operationSequence xsi:nil="true" xmlns:xsi="http://www.w3.org/2001/XMLSchema-instance"/>
                            <ns3:theAirspaceVolume>
                                <ns3:AirspaceVolume>
                                    <ns3:minimumLimit uom="FT">2600</ns3:minimumLimit>
                                    <ns3:minimumLimitReference>MSL</ns3:minimumLimitReference>
                                    <ns3:horizontalProjection>
                                        <ns3:Surface srsName="urn:ogc:def:crs:OGC:1.3:CRS84" ns1:id="c5956393-9e2e-4b3f-a67c-b0d091f03a1d">
                                            <ns1:patches>
                                                <ns1:PolygonPatch interpolation="planar">
                                                    <ns1:exterior>
                                                        <ns1:LinearRing>
                                                            <ns1:posList>-86.61389 40.43985 -86.61715 40.43978 -86.62041 40.43959 -86.62365 40.43928 -86.62687 40.43885 -86.63005 40.4383 -86.6332 40.43763 -86.6363 40.43684 -86.63934 40.43594 -86.64232 40.43492 -86.64524 40.4338 -86.64807 40.43257 -86.65083 40.43123 -86.65349 40.42979 -86.65606 40.42826 -86.65853 40.42663 -86.66089 40.42491 -86.66313 40.4231 -86.66526 40.42122 -86.66726 40.41925 -86.66913 40.41721 -86.67087 40.41511 -86.67247 40.41294 -86.67393 40.41072 -86.67525 40.40844 -86.67642 40.40612 -86.67743 40.40375 -86.67829 40.40135 -86.679 40.39893 -86.67955 40.39647 -86.67994 40.394 -86.68017 40.39152 -86.68024 40.38904 -86.68015 40.38655 -86.6799 40.38407 -86.67949 40.3816 -86.67892 40.37915 -86.6782 40.37672 -86.67732 40.37433 -86.67628 40.37197 -86.6751 40.36965 -86.67377 40.36738 -86.67229 40.36516 -86.67067 40.36299 -86.66892 40.3609 -86.66703 40.35886 -86.66501 40.35691 -86.66287 40.35503 -86.66061 40.35323 -86.65824 40.35152 -86.65576 40.3499 -86.65318 40.34837 -86.6505 40.34695 -86.64774 40.34562 -86.64489 40.3444 -86.64197 40.34329 -86.63898 40.34228 -86.63593 40.34139 -86.63282 40.34062 -86.62967 40.33996 -86.62648 40.33943 -86.62327 40.33901 -86.62002 40.33871 -86.61676 40.33853 -86.61389 40.33848 -86.61062 40.33855 -86.60737 40.33874 -86.60413 40.33905 -86.60091 40.33948 -86.59773 40.34003 -86.59458 40.34071 -86.59148 40.34149 -86.58844 40.3424 -86.58546 40.34341 -86.58254 40.34454 -86.57971 40.34577 -86.57695 40.34711 -86.57429 40.34855 -86.57172 40.35008 -86.56925 40.35171 -86.56689 40.35343 -86.56464 40.35524 -86.56252 40.35713 -86.56052 40.3591 -86.55864 40.36114 -86.5569 40.36324 -86.5553 40.36541 -86.55384 40.36764 -86.55252 40.36992 -86.55136 40.37224 -86.55034 40.3746 -86.54948 40.377 -86.54877 40.37943 -86.54822 40.38189 -86.54783 40.38436 -86.5476 40.38684 -86.54753 40.38933 -86.54762 40.39181 -86.54787 40.39429 -86.54828 40.39676 -86.54885 40.39921 -86.54957 40.40164 -86.55045 40.40403 -86.55148 40.40639 -86.55267 40.40871 -86.554 40.41098 -86.55548 40.4132 -86.55709 40.41536 -86.55885 40.41745 -86.56074 40.41948 -86.56275 40.42144 -86.56489 40.42332 -86.56715 40.42511 -86.56952 40.42682 -86.572 40.42844 -86.57458 40.42997 -86.57726 40.43139 -86.58002 40.43272 -86.58287 40.43394 -86.58579 40.43505 -86.58878 40.43605 -86.59183 40.43694 -86.59494 40.43771 -86.59809 40.43837 -86.60128 40.4389 -86.6045 40.43932 -86.60774 40.43962 -86.611 40.4398 -86.61389 40.43985</ns1:posList>
                                                        </ns1:LinearRing>
                                                    </ns1:exterior>
                                                </ns1:PolygonPatch>
                                            </ns1:patches>
                                        </ns3:Surface>
                                    </ns3:horizontalProjection>
                                </ns3:AirspaceVolume>
                            </ns3:theAirspaceVolume>
                        </ns3:AirspaceGeometryComponent>
                    </ns3:geometryComponent>
                </ns3:AirspaceTimeSlice>
            </ns3:timeSlice>
        </ns3:Airspace>
    </ns8:hasMember>
    <ns8:hasMember ns2:type="simple">
        <ns3:Airspace ns1:id="19329395">
            <ns1:description ns2:type="simple">MINIMUM VECTORING ALTITUDE (MVA)</ns1:description>
            <ns1:boundedBy xsi:nil="true" xmlns:xsi="http://www.w3.org/2001/XMLSchema-instance"/>
            <ns3:timeSlice>
                <ns3:AirspaceTimeSlice>
                    <ns1:validTime ns2:type="simple">
                        <ns1:TimePeriod>
                            <ns1:beginPosition>1980-01-01T14:00:00Z</ns1:beginPosition>
                            <ns1:endPosition indeterminatePosition="unknown"/>
                        </ns1:TimePeriod>
                    </ns1:validTime>
                    <ns3:interpretation>BASELINE</ns3:interpretation>
                    <ns3:sequenceNumber>1</ns3:sequenceNumber>
                    <ns3:type>OTHER</ns3:type>
                    <ns3:designator xsi:nil="true" xmlns:xsi="http://www.w3.org/2001/XMLSchema-instance"/>
                    <ns3:localType xsi:nil="true" xmlns:xsi="http://www.w3.org/2001/XMLSchema-instance"/>
                    <ns3:name>I</ns3:name>
                    <ns3:designatorICAO xsi:nil="true" xmlns:xsi="http://www.w3.org/2001/XMLSchema-instance"/>
                    <ns3:controlType xsi:nil="true" xmlns:xsi="http://www.w3.org/2001/XMLSchema-instance"/>
                    <ns3:upperLowerSeparation xsi:nil="true" xmlns:xsi="http://www.w3.org/2001/XMLSchema-instance"/>
                    <ns3:protectedRoute xsi:nil="true" xmlns:xsi="http://www.w3.org/2001/XMLSchema-instance"/>
                    <ns3:geometryComponent>
                        <ns3:AirspaceGeometryComponent>
                            <ns3:operation xsi:nil="true" xmlns:xsi="http://www.w3.org/2001/XMLSchema-instance"/>
                            <ns3:operationSequence xsi:nil="true" xmlns:xsi="http://www.w3.org/2001/XMLSchema-instance"/>
                            <ns3:theAirspaceVolume>
                                <ns3:AirspaceVolume>
                                    <ns3:minimumLimit uom="FT">2800</ns3:minimumLimit>
                                    <ns3:minimumLimitReference>MSL</ns3:minimumLimitReference>
                                    <ns3:horizontalProjection>
                                        <ns3:Surface srsName="urn:ogc:def:crs:OGC:1.3:CRS84" ns1:id="c4ef551b-9e36-47e9-a220-7a0be5005f21">
                                            <ns1:patches>
                                                <ns1:PolygonPatch interpolation="planar">
                                                    <ns1:exterior>
                                                        <ns1:LinearRing>
                                                            <ns1:posList>-87.37164 40.52043 -87.42234 40.47908 -87.47031 40.43587 -87.51544 40.39088 -87.55761 40.34423 -87.59673 40.29603 -87.63269 40.24639 -87.66543 40.19542 -87.69484 40.14325 -87.72088 40.08999 -87.74346 40.03578 -87.76254 39.98074 -87.77807 39.92501 -87.79002 39.86872 -87.79835 39.81199 -87.80305 39.75497 -87.8041 39.6978 -87.80391 39.68799 -87.80099 39.6308 -87.79443 39.57375 -87.78424 39.51696 -87.77045 39.46058 -87.7531 39.40475 -87.73222 39.3496 -87.70786 39.29526 -87.68008 39.24187 -87.64896 39.18956 -87.61456 39.13847 -87.57696 39.0887 -87.53627 39.0404 -87.49257 38.99367 -87.44597 38.94863 -87.39659 38.9054 -87.34454 38.86408 -87.28995 38.82478 -87.23295 38.78759 -87.17367 38.75261 -87.11226 38.71992 -87.04888 38.68961 -86.98366 38.66175 -86.91677 38.63641 -86.84837 38.61366 -86.77862 38.59355 -86.70769 38.57614 -86.63576 38.56146 -86.56299 38.54956 -86.48956 38.54047 -86.41565 38.5342 -86.34144 38.53078 -86.29255 38.53008 -86.21823 38.53163 -86.1441 38.53602 -86.07034 38.54326 -85.99712 38.55332 -85.92462 38.56617 -85.85301 38.58179 -85.78247 38.60013 -85.71316 38.62115 -85.64526 38.64479 -85.57892 38.671 -85.51431 38.69971 -85.45159 38.73084 -85.39089 38.76433 -85.33238 38.80007 -85.27619 38.838 -85.22245 38.878 -85.1713 38.91999 -85.12286 38.96385 -85.07724 39.00948 -85.03456 39.05676 -84.99491 39.10558 -84.9584 39.15581 -84.92512 39.20734 -84.89513 39.26003 -84.86852 39.31376 -84.84534 39.36839 -84.82566 39.42379 -84.80952 39.47982 -84.79696 39.53636 -84.78802 39.59325 -84.7827 39.65037 -84.78119 39.68799 -84.78161 39.74518 -84.78569 39.80223 -84.79339 39.85901 -84.80472 39.91539 -84.81964 39.97123 -84.83812 40.0264 -84.8601 40.08076 -84.88555 40.13419 -84.91439 40.18655 -84.94656 40.23774 -84.98198 40.28762 -85.02056 40.33607 -85.06222 40.383 -85.10685 40.42827 -85.15434 40.4718 -85.20458 40.51348 -85.21346 40.52043 -85.26676 40.55981 -85.32255 40.59714 -85.38067 40.63232 -85.441 40.66528 -85.50339 40.69594 -85.56769 40.72423 -85.63374 40.75008 -85.70139 40.77344 -85.77047 40.79424 -85.84081 40.81245 -85.91225 40.82802 -85.98461 40.84092 -86.05772 40.85111 -86.13141 40.85858 -86.20549 40.8633 -86.27979 40.86527 -86.29255 40.86533 -86.36687 40.86384 -86.441 40.85959 -86.51476 40.85259 -86.58798 40.84286 -86.66049 40.83043 -86.7321 40.81531 -86.80264 40.79755 -86.87195 40.77719 -86.93985 40.75427 -87.00619 40.72884 -87.0708 40.70097 -87.13353 40.67071 -87.19422 40.63814 -87.25274 40.60333 -87.30893 40.56637 -87.36267 40.52733 -87.37164 40.52043</ns1:posList>
                                                        </ns1:LinearRing>
                                                    </ns1:exterior>
                                                    <ns1:interior>
                                                        <ns1:LinearRing>
                                                            <ns1:posList>-84.8914 39.81117 -84.90075 39.86739 -84.91369 39.92315 -84.93018 39.97831 -84.95017 40.03274 -84.97363 40.0863 -85.0005 40.13888 -85.03071 40.19036 -85.06418 40.24059 -85.09711 40.28475 -85.13563 40.32887 -85.17695 40.37147 -85.22096 40.41244 -85.26755 40.4517 -85.31662 40.48915 -85.36805 40.5247 -85.4217 40.55828 -85.47746 40.5898 -85.53519 40.61918 -85.59475 40.64638 -85.656 40.67131 -85.71879 40.69392 -85.78296 40.71416 -85.84836 40.73199 -85.91485 40.74736 -85.98224 40.76023 -86.05039 40.77059 -86.11913 40.77839 -86.18829 40.78364 -86.25771 40.7863 -86.2889 40.78666 -86.35792 40.78527 -86.42676 40.78132 -86.49527 40.77481 -86.56327 40.76577 -86.6306 40.7542 -86.6971 40.74015 -86.76262 40.72363 -86.82698 40.7047 -86.89004 40.68339 -86.95165 40.65975 -87.01165 40.63383 -87.06991 40.60571 -87.12627 40.57543 -87.18061 40.54307 -87.2328 40.50871 -87.2827 40.47243 -87.29038 40.46652 -87.33749 40.42811 -87.38207 40.38797 -87.42401 40.34618 -87.46321 40.30285 -87.49957 40.25808 -87.53301 40.21196 -87.56344 40.16462 -87.5908 40.11616 -87.61501 40.0667 -87.63602 40.01635 -87.65378 39.96523 -87.66824 39.91347 -87.67938 39.86119 -87.68715 39.80851 -87.69155 39.75556 -87.69257 39.70246 -87.69242 39.69406 -87.68979 39.64096 -87.68378 39.58798 -87.6744 39.53525 -87.66168 39.4829 -87.64564 39.43105 -87.62633 39.37984 -87.60379 39.32939 -87.57807 39.27981 -87.54924 39.23124 -87.51737 39.18379 -87.48253 39.13758 -87.44481 39.09272 -87.4043 39.04932 -87.3611 39.00749 -87.3153 38.96734 -87.26702 38.92896 -87.21638 38.89245 -87.1635 38.8579 -87.10851 38.82539 -87.05153 38.79502 -86.99271 38.76684 -86.93219 38.74095 -86.87011 38.71739 -86.80663 38.69622 -86.74189 38.67751 -86.67605 38.6613 -86.60927 38.64763 -86.54171 38.63653 -86.47354 38.62803 -86.40492 38.62215 -86.33601 38.61891 -86.2889 38.61822 -86.21989 38.61965 -86.15105 38.62373 -86.08255 38.63044 -86.01456 38.63977 -85.94723 38.65169 -85.88073 38.66618 -85.81523 38.68319 -85.75087 38.70268 -85.68781 38.72461 -85.62621 38.74892 -85.56622 38.77555 -85.50797 38.80443 -85.45161 38.83549 -85.39727 38.86866 -85.34509 38.90384 -85.29519 38.94095 -85.24769 38.97991 -85.2027 39.0206 -85.16034 39.06294 -85.1207 39.10682 -85.08389 39.15212 -85.04999 39.19874 -85.01907 39.24656 -84.99123 39.29546 -84.96651 39.34533 -84.94499 39.39604 -84.92672 39.44746 -84.91173 39.49948 -84.90006 39.55197 -84.89175 39.60479 -84.88682 39.65782 -84.88539 39.69406 -84.88508 39.73539 -84.88741 39.77665 -84.8914 39.81117</ns1:posList>
                                                        </ns1:LinearRing>
                                                    </ns1:interior>
                                                </ns1:PolygonPatch>
                                            </ns1:patches>
                                        </ns3:Surface>
                                    </ns3:horizontalProjection>
                                </ns3:AirspaceVolume>
                            </ns3:theAirspaceVolume>
                        </ns3:AirspaceGeometryComponent>
                    </ns3:geometryComponent>
                </ns3:AirspaceTimeSlice>
            </ns3:timeSlice>
        </ns3:Airspace>
    </ns8:hasMember>
    <ns8:hasMember ns2:type="simple">
        <ns3:Airspace ns1:id="19329685">
            <ns1:description ns2:type="simple">MINIMUM VECTORING ALTITUDE (MVA)</ns1:description>
            <ns1:boundedBy xsi:nil="true" xmlns:xsi="http://www.w3.org/2001/XMLSchema-instance"/>
            <ns3:timeSlice>
                <ns3:AirspaceTimeSlice>
                    <ns1:validTime ns2:type="simple">
                        <ns1:TimePeriod>
                            <ns1:beginPosition>1980-01-01T14:00:00Z</ns1:beginPosition>
                            <ns1:endPosition indeterminatePosition="unknown"/>
                        </ns1:TimePeriod>
                    </ns1:validTime>
                    <ns3:interpretation>BASELINE</ns3:interpretation>
                    <ns3:sequenceNumber>1</ns3:sequenceNumber>
                    <ns3:type>OTHER</ns3:type>
                    <ns3:designator xsi:nil="true" xmlns:xsi="http://www.w3.org/2001/XMLSchema-instance"/>
                    <ns3:localType xsi:nil="true" xmlns:xsi="http://www.w3.org/2001/XMLSchema-instance"/>
                    <ns3:name>J</ns3:name>
                    <ns3:designatorICAO xsi:nil="true" xmlns:xsi="http://www.w3.org/2001/XMLSchema-instance"/>
                    <ns3:controlType xsi:nil="true" xmlns:xsi="http://www.w3.org/2001/XMLSchema-instance"/>
                    <ns3:upperLowerSeparation xsi:nil="true" xmlns:xsi="http://www.w3.org/2001/XMLSchema-instance"/>
                    <ns3:protectedRoute xsi:nil="true" xmlns:xsi="http://www.w3.org/2001/XMLSchema-instance"/>
                    <ns3:geometryComponent>
                        <ns3:AirspaceGeometryComponent>
                            <ns3:operation xsi:nil="true" xmlns:xsi="http://www.w3.org/2001/XMLSchema-instance"/>
                            <ns3:operationSequence xsi:nil="true" xmlns:xsi="http://www.w3.org/2001/XMLSchema-instance"/>
                            <ns3:theAirspaceVolume>
                                <ns3:AirspaceVolume>
                                    <ns3:minimumLimit uom="FT">2600</ns3:minimumLimit>
                                    <ns3:minimumLimitReference>MSL</ns3:minimumLimitReference>
                                    <ns3:horizontalProjection>
                                        <ns3:Surface srsName="urn:ogc:def:crs:OGC:1.3:CRS84" ns1:id="af3effaa-378f-4a88-be34-5f7e4d2674de">
                                            <ns1:patches>
                                                <ns1:PolygonPatch interpolation="planar">
                                                    <ns1:exterior>
                                                        <ns1:LinearRing>
                                                            <ns1:posList>-87.39128 39.19167 -87.38807 39.19174 -87.38487 39.19193 -87.38168 39.19224 -87.37851 39.19267 -87.37538 39.19323 -87.37229 39.1939 -87.36924 39.19469 -87.36625 39.19559 -87.36331 39.19661 -87.36045 39.19773 -87.35766 39.19897 -87.35495 39.2003 -87.35233 39.20174 -87.3498 39.20328 -87.34737 39.20491 -87.34505 39.20664 -87.34284 39.20844 -87.34075 39.21033 -87.33878 39.2123 -87.33694 39.21434 -87.33523 39.21645 -87.33366 39.21862 -87.33222 39.22084 -87.33093 39.22312 -87.32978 39.22545 -87.32878 39.22781 -87.32793 39.23021 -87.32724 39.23264 -87.3267 39.2351 -87.32632 39.23757 -87.32609 39.24005 -87.32602 39.24254 -87.32611 39.24502 -87.32635 39.2475 -87.32676 39.24997 -87.32732 39.25242 -87.32803 39.25485 -87.3289 39.25724 -87.32991 39.2596 -87.33108 39.26192 -87.33239 39.26419 -87.33384 39.26641 -87.33543 39.26857 -87.33716 39.27067 -87.33902 39.2727 -87.341 39.27465 -87.34311 39.27653 -87.34533 39.27833 -87.34767 39.28004 -87.3501 39.28166 -87.35264 39.28318 -87.35528 39.28461 -87.35799 39.28593 -87.3608 39.28715 -87.36367 39.28826 -87.36661 39.28926 -87.36961 39.29015 -87.37267 39.29092 -87.37576 39.29158 -87.3789 39.29212 -87.38207 39.29253 -87.38526 39.29283 -87.38846 39.29301 -87.39128 39.29306 -87.39449 39.29299 -87.39769 39.2928 -87.40088 39.29249 -87.40405 39.29206 -87.40718 39.2915 -87.41027 39.29083 -87.41332 39.29005 -87.41631 39.28915 -87.41925 39.28813 -87.42211 39.28701 -87.4249 39.28577 -87.42761 39.28444 -87.43023 39.283 -87.43276 39.28146 -87.43519 39.27983 -87.43751 39.27811 -87.43972 39.27631 -87.44181 39.27442 -87.44378 39.27245 -87.44562 39.27042 -87.44733 39.26831 -87.4489 39.26614 -87.45034 39.26392 -87.45163 39.26164 -87.45278 39.25932 -87.45378 39.25695 -87.45463 39.25455 -87.45532 39.25212 -87.45586 39.24967 -87.45624 39.2472 -87.45647 39.24472 -87.45654 39.24223 -87.45645 39.23974 -87.45621 39.23726 -87.4558 39.23479 -87.45524 39.23234 -87.45453 39.22992 -87.45366 39.22752 -87.45265 39.22516 -87.45148 39.22284 -87.45017 39.22057 -87.44872 39.21835 -87.44713 39.21618 -87.4454 39.21409 -87.44354 39.21206 -87.44156 39.2101 -87.43945 39.20822 -87.43723 39.20642 -87.43489 39.20471 -87.43246 39.20309 -87.42992 39.20156 -87.42728 39.20013 -87.42457 39.19881 -87.42176 39.19759 -87.41889 39.19648 -87.41595 39.19547 -87.41295 39.19458 -87.40989 39.19381 -87.4068 39.19315 -87.40366 39.19261 -87.40049 39.1922 -87.3973 39.1919 -87.3941 39.19172 -87.39128 39.19167</ns1:posList>
                                                        </ns1:LinearRing>
                                                    </ns1:exterior>
                                                </ns1:PolygonPatch>
                                            </ns1:patches>
                                        </ns3:Surface>
                                    </ns3:horizontalProjection>
                                </ns3:AirspaceVolume>
                            </ns3:theAirspaceVolume>
                        </ns3:AirspaceGeometryComponent>
                    </ns3:geometryComponent>
                </ns3:AirspaceTimeSlice>
            </ns3:timeSlice>
        </ns3:Airspace>
    </ns8:hasMember>
</ns8:AIXMBasicMessage>
