<?xml version="1.0" encoding="UTF-8" standalone="yes"?>
<ns8:AIXMBasicMessage ns1:id="aaafa17a-070a-470a-947c-0a086be0dd7f" xmlns:ns6="http://www.isotc211.org/2005/gmx" xmlns:ns5="http://www.isotc211.org/2005/gmd" xmlns:ns8="http://www.aixm.aero/schema/5.1/message" xmlns:ns7="http://www.isotc211.org/2005/gts" xmlns:ns2="http://www.w3.org/1999/xlink" xmlns:ns1="http://www.opengis.net/gml/3.2" xmlns:ns4="http://www.isotc211.org/2005/gco" xmlns:ns3="http://www.aixm.aero/schema/5.1">
    <ns1:description ns2:type="simple">MLU_MVA_FUS3_2022</ns1:description>
    <ns1:boundedBy xsi:nil="true" xmlns:xsi="http://www.w3.org/2001/XMLSchema-instance"/>
    <ns3:sequenceNumber>1</ns3:sequenceNumber>
    <ns3:messageMetadata/>
    <ns8:hasMember ns2:type="simple">
        <ns3:Airspace ns1:id="19336119">
            <ns1:description ns2:type="simple">MINIMUM VECTORING ALTITUDE (MVA)</ns1:description>
            <ns1:boundedBy xsi:nil="true" xmlns:xsi="http://www.w3.org/2001/XMLSchema-instance"/>
            <ns3:timeSlice>
                <ns3:AirspaceTimeSlice>
                    <ns1:validTime ns2:type="simple">
                        <ns1:TimePeriod>
                            <ns1:beginPosition>1980-01-01T14:00:00Z</ns1:beginPosition>
                            <ns1:endPosition indeterminatePosition="unknown"/>
                        </ns1:TimePeriod>
                    </ns1:validTime>
                    <ns3:interpretation>BASELINE</ns3:interpretation>
                    <ns3:sequenceNumber>1</ns3:sequenceNumber>
                    <ns3:type>OTHER</ns3:type>
                    <ns3:designator xsi:nil="true" xmlns:xsi="http://www.w3.org/2001/XMLSchema-instance"/>
                    <ns3:localType xsi:nil="true" xmlns:xsi="http://www.w3.org/2001/XMLSchema-instance"/>
                    <ns3:name>A</ns3:name>
                    <ns3:designatorICAO xsi:nil="true" xmlns:xsi="http://www.w3.org/2001/XMLSchema-instance"/>
                    <ns3:controlType xsi:nil="true" xmlns:xsi="http://www.w3.org/2001/XMLSchema-instance"/>
                    <ns3:upperLowerSeparation xsi:nil="true" xmlns:xsi="http://www.w3.org/2001/XMLSchema-instance"/>
                    <ns3:protectedRoute xsi:nil="true" xmlns:xsi="http://www.w3.org/2001/XMLSchema-instance"/>
                    <ns3:geometryComponent>
                        <ns3:AirspaceGeometryComponent>
                            <ns3:operation xsi:nil="true" xmlns:xsi="http://www.w3.org/2001/XMLSchema-instance"/>
                            <ns3:operationSequence xsi:nil="true" xmlns:xsi="http://www.w3.org/2001/XMLSchema-instance"/>
                            <ns3:theAirspaceVolume>
                                <ns3:AirspaceVolume>
                                    <ns3:minimumLimit uom="FT">1800</ns3:minimumLimit>
                                    <ns3:minimumLimitReference>MSL</ns3:minimumLimitReference>
                                    <ns3:horizontalProjection>
                                        <ns3:Surface srsName="urn:ogc:def:crs:OGC:1.3:CRS84" ns1:id="2e710986-f21b-4c22-ae31-d8c43b2c871c">
                                            <ns1:patches>
                                                <ns1:PolygonPatch interpolation="planar">
                                                    <ns1:exterior>
                                                        <ns1:LinearRing>
                                                            <ns1:posList>-92.018 31.84283 -91.97921 31.84349 -91.9405 31.84576 -91.90198 31.84965 -91.86372 31.85514 -91.82583 31.86221 -91.78839 31.87086 -91.75149 31.88105 -91.71523 31.89277 -91.67969 31.90598 -91.64496 31.92065 -91.61111 31.93675 -91.57824 31.95424 -91.54642 31.97307 -91.51572 31.9932 -91.48623 32.01458 -91.45801 32.03715 -91.43113 32.06086 -91.40566 32.08566 -91.38165 32.11148 -91.35916 32.13826 -91.33826 32.16593 -91.31898 32.19443 -91.30138 32.22368 -91.2855 32.25362 -91.27137 32.28417 -91.25903 32.31527 -91.24852 32.34682 -91.23984 32.37877 -91.23304 32.41102 -91.22811 32.4435 -91.22508 32.47614 -91.22396 32.50885 -91.22473 32.54156 -91.22741 32.57418 -91.23199 32.60664 -91.23845 32.63886 -91.24677 32.67076 -91.25695 32.70227 -91.26896 32.73332 -91.28276 32.76381 -91.29832 32.79369 -91.3156 32.82289 -91.33457 32.85132 -91.35518 32.87894 -91.37738 32.90566 -91.40111 32.93142 -91.42632 32.95617 -91.45294 32.97985 -91.48092 33.00239 -91.51018 33.02376 -91.54066 33.04388 -91.57228 33.06273 -91.60496 33.08025 -91.63864 33.0964 -91.67321 33.11114 -91.70861 33.12444 -91.74474 33.13628 -91.78153 33.14661 -91.81887 33.15541 -91.85669 33.16267 -91.89489 33.16837 -91.93337 33.17249 -91.97205 33.17503 -92.01083 33.17597 -92.018 33.17597 -92.05679 33.17517 -92.09548 33.17278 -92.13398 33.16881 -92.17221 33.16325 -92.21007 33.15614 -92.24746 33.14747 -92.2843 33.13728 -92.32049 33.12559 -92.35596 33.11242 -92.39062 33.09781 -92.42437 33.08178 -92.45715 33.06439 -92.48887 33.04566 -92.51946 33.02565 -92.54884 33.0044 -92.57693 32.98196 -92.60369 32.95839 -92.62903 32.93373 -92.6529 32.90806 -92.67523 32.88142 -92.69599 32.85389 -92.71511 32.82553 -92.73256 32.7964 -92.74828 32.76658 -92.76224 32.73614 -92.77441 32.70514 -92.78476 32.67367 -92.79326 32.6418 -92.79989 32.60961 -92.80464 32.57717 -92.80749 32.54456 -92.80844 32.51185 -92.80749 32.47914 -92.80463 32.44649 -92.79988 32.41399 -92.79325 32.38172 -92.78475 32.34974 -92.7744 32.31815 -92.76223 32.28701 -92.74826 32.25641 -92.73254 32.22641 -92.71509 32.19709 -92.69597 32.16851 -92.67521 32.14076 -92.65287 32.1139 -92.629 32.08799 -92.60366 32.0631 -92.57691 32.03928 -92.54881 32.0166 -92.51943 31.99512 -92.48884 31.97487 -92.45712 31.95592 -92.42434 31.93831 -92.39058 31.92208 -92.35593 31.90727 -92.32046 31.89392 -92.28426 31.88207 -92.24742 31.87173 -92.21003 31.86295 -92.17217 31.85573 -92.13395 31.8501 -92.09544 31.84606 -92.05675 31.84364 -92.018 31.84283</ns1:posList>
                                                        </ns1:LinearRing>
                                                    </ns1:exterior>
                                                    <ns1:interior>
                                                        <ns1:LinearRing>
                                                            <ns1:posList>-92.22525 33.12895 -92.22822 33.12888 -92.23118 33.12869 -92.23413 33.12838 -92.23706 33.12794 -92.23995 33.12739 -92.24282 33.12672 -92.24563 33.12593 -92.2484 33.12502 -92.25111 33.12401 -92.25376 33.12288 -92.25634 33.12164 -92.25885 33.12031 -92.26127 33.11887 -92.26361 33.11733 -92.26585 33.1157 -92.268 33.11397 -92.27004 33.11216 -92.27197 33.11027 -92.27379 33.10831 -92.27549 33.10627 -92.27708 33.10416 -92.27853 33.10199 -92.27986 33.09976 -92.28105 33.09748 -92.28211 33.09516 -92.28303 33.09279 -92.28382 33.09039 -92.28446 33.08796 -92.28496 33.0855 -92.28531 33.08303 -92.28552 33.08055 -92.28558 33.07806 -92.2855 33.07557 -92.28527 33.07308 -92.28489 33.07061 -92.28437 33.06816 -92.28371 33.06573 -92.28291 33.06334 -92.28197 33.06097 -92.28089 33.05865 -92.27968 33.05638 -92.27833 33.05416 -92.27686 33.052 -92.27526 33.0499 -92.27354 33.04787 -92.2717 33.04591 -92.26975 33.04403 -92.2677 33.04223 -92.26554 33.04052 -92.26328 33.0389 -92.26093 33.03737 -92.2585 33.03594 -92.25598 33.03462 -92.25339 33.0334 -92.25073 33.03229 -92.24801 33.03129 -92.24523 33.0304 -92.24241 33.02962 -92.23954 33.02897 -92.23664 33.02843 -92.23371 33.02801 -92.23076 33.02772 -92.2278 33.02754 -92.22525 33.02749 -92.22228 33.02756 -92.21932 33.02775 -92.21637 33.02807 -92.21344 33.0285 -92.21055 33.02905 -92.20768 33.02973 -92.20487 33.03052 -92.2021 33.03142 -92.19939 33.03244 -92.19674 33.03357 -92.19416 33.0348 -92.19165 33.03614 -92.18923 33.03758 -92.18689 33.03912 -92.18465 33.04076 -92.1825 33.04248 -92.18046 33.04429 -92.17853 33.04618 -92.17671 33.04815 -92.17501 33.05019 -92.17342 33.0523 -92.17197 33.05447 -92.17064 33.0567 -92.16945 33.05898 -92.16839 33.06131 -92.16747 33.06368 -92.16668 33.06608 -92.16604 33.06851 -92.16554 33.07097 -92.16519 33.07344 -92.16498 33.07592 -92.16492 33.07841 -92.165 33.0809 -92.16523 33.08338 -92.16561 33.08585 -92.16613 33.08831 -92.16679 33.09073 -92.16759 33.09313 -92.16853 33.09549 -92.16961 33.09781 -92.17082 33.10008 -92.17217 33.1023 -92.17364 33.10446 -92.17524 33.10656 -92.17696 33.10859 -92.1788 33.11055 -92.18075 33.11243 -92.1828 33.11422 -92.18496 33.11593 -92.18722 33.11755 -92.18957 33.11908 -92.192 33.1205 -92.19452 33.12183 -92.19711 33.12305 -92.19977 33.12416 -92.20249 33.12516 -92.20527 33.12605 -92.20809 33.12682 -92.21096 33.12747 -92.21386 33.12801 -92.21679 33.12843 -92.21974 33.12872 -92.2227 33.1289 -92.22525 33.12895</ns1:posList>
                                                        </ns1:LinearRing>
                                                    </ns1:interior>
                                                    <ns1:interior>
                                                        <ns1:LinearRing>
                                                            <ns1:posList>-92.03914 32.69218 -92.04107 32.69408 -92.04312 32.69589 -92.04526 32.69762 -92.04751 32.69925 -92.04984 32.70079 -92.05227 32.70224 -92.05477 32.70358 -92.05735 32.70481 -92.06 32.70594 -92.06271 32.70696 -92.06548 32.70786 -92.06829 32.70865 -92.07115 32.70932 -92.07405 32.70988 -92.07697 32.71031 -92.07992 32.71062 -92.08288 32.71081 -92.08585 32.71088 -92.08881 32.71082 -92.09177 32.71064 -92.09472 32.71034 -92.09765 32.70992 -92.10055 32.70938 -92.10341 32.70872 -92.10623 32.70794 -92.109 32.70705 -92.11172 32.70604 -92.11437 32.70492 -92.11696 32.70369 -92.11947 32.70236 -92.1219 32.70093 -92.12425 32.6994 -92.1265 32.69777 -92.12865 32.69605 -92.13071 32.69424 -92.13265 32.69236 -92.13448 32.69039 -92.1362 32.68835 -92.13779 32.68624 -92.13926 32.68407 -92.1406 32.68184 -92.14181 32.67956 -92.14288 32.67723 -92.14382 32.67486 -92.14462 32.67245 -92.14528 32.67001 -92.14579 32.66755 -92.14616 32.66507 -92.14639 32.66258 -92.14646 32.66008 -92.1464 32.65758 -92.14619 32.65509 -92.14583 32.65261 -92.14533 32.65015 -92.14468 32.64771 -92.1439 32.6453 -92.14297 32.64292 -92.14191 32.64059 -92.14072 32.6383 -92.13939 32.63606 -92.13793 32.63388 -92.13635 32.63177 -92.13464 32.62972 -92.13282 32.62775 -92.13089 32.62585 -92.12884 32.62404 -92.1267 32.62231 -92.12446 32.62067 -92.12212 32.61913 -92.1197 32.61768 -92.11719 32.61634 -92.11461 32.6151 -92.11196 32.61397 -92.10925 32.61296 -92.10648 32.61205 -92.10367 32.61126 -92.10081 32.61059 -92.09791 32.61004 -92.09499 32.6096 -92.09204 32.60929 -92.08908 32.6091 -92.08612 32.60903 -92.08315 32.60909 -92.08019 32.60927 -92.07724 32.60957 -92.07431 32.60999 -92.07141 32.61053 -92.06855 32.6112 -92.06573 32.61197 -92.06296 32.61287 -92.06024 32.61388 -92.05759 32.615 -92.055 32.61622 -92.05249 32.61756 -92.05006 32.61899 -92.04771 32.62053 -92.04546 32.62216 -92.04331 32.62388 -92.04126 32.62568 -92.03931 32.62757 -92.03835 32.62858 -92.03642 32.62667 -92.03437 32.62485 -92.03223 32.62311 -92.02998 32.62146 -92.02764 32.61991 -92.02521 32.61845 -92.0227 32.6171 -92.02012 32.61585 -92.01747 32.61472 -92.01475 32.61369 -92.01198 32.61277 -92.00915 32.61197 -92.00629 32.61129 -92.00338 32.61073 -92.00045 32.61029 -91.9975 32.60997 -91.99453 32.60978 -91.99155 32.6097 -91.98857 32.60975 -91.9856 32.60992 -91.98264 32.61022 -91.9797 32.61064 -91.9768 32.61117 -91.97392 32.61183 -91.97109 32.61261 -91.9683 32.6135 -91.96558 32.6145 -91.96291 32.61562 -91.96031 32.61685 -91.95779 32.61818 -91.95534 32.61961 -91.95299 32.62115 -91.95072 32.62278 -91.94855 32.6245 -91.94649 32.6263 -91.94453 32.6282 -91.94269 32.63017 -91.94096 32.63221 -91.93936 32.63432 -91.93788 32.6365 -91.93652 32.63873 -91.9353 32.64102 -91.93422 32.64336 -91.93327 32.64573 -91.93246 32.64815 -91.93179 32.65059 -91.93127 32.65306 -91.93089 32.65555 -91.93066 32.65805 -91.93057 32.66056 -91.93063 32.66306 -91.93083 32.66556 -91.93118 32.66805 -91.93168 32.67053 -91.93232 32.67298 -91.9331 32.6754 -91.93402 32.67778 -91.93508 32.68012 -91.93627 32.68242 -91.9376 32.68466 -91.93905 32.68685 -91.94063 32.68898 -91.94234 32.69103 -91.94416 32.69302 -91.94609 32.69492 -91.94814 32.69675 -91.95028 32.69848 -91.95253 32.70013 -91.95487 32.70168 -91.9573 32.70313 -91.9598 32.70449 -91.96239 32.70573 -91.96504 32.70687 -91.96776 32.7079 -91.97053 32.70881 -91.97336 32.70961 -91.97622 32.71029 -91.97913 32.71085 -91.98206 32.71129 -91.98501 32.71161 -91.98798 32.7118 -91.99096 32.71188 -91.99394 32.71183 -91.99691 32.71166 -91.99987 32.71136 -92.0028 32.71094 -92.00571 32.71041 -92.00859 32.70975 -92.01142 32.70898 -92.0142 32.70809 -92.01693 32.70708 -92.0196 32.70596 -92.0222 32.70474 -92.02472 32.70341 -92.02717 32.70198 -92.02952 32.70044 -92.03179 32.69882 -92.03396 32.6971 -92.03602 32.69529 -92.03798 32.6934 -92.03914 32.69218</ns1:posList>
                                                        </ns1:LinearRing>
                                                    </ns1:interior>
                                                    <ns1:interior>
                                                        <ns1:LinearRing>
                                                            <ns1:posList>-92.71222 32.49462 -92.70927 32.49455 -92.70633 32.49436 -92.7034 32.49404 -92.7005 32.49361 -92.69762 32.49306 -92.69478 32.49238 -92.69198 32.4916 -92.68923 32.49069 -92.68654 32.48968 -92.68391 32.48855 -92.68135 32.48731 -92.67886 32.48598 -92.67645 32.48453 -92.67413 32.483 -92.67191 32.48136 -92.66978 32.47964 -92.66775 32.47783 -92.66583 32.47594 -92.66402 32.47397 -92.66233 32.47193 -92.66076 32.46983 -92.65932 32.46766 -92.658 32.46543 -92.65681 32.46315 -92.65576 32.46082 -92.65485 32.45846 -92.65407 32.45606 -92.65343 32.45362 -92.65294 32.45117 -92.65259 32.4487 -92.65238 32.44621 -92.65232 32.44372 -92.6524 32.44124 -92.65263 32.43875 -92.653 32.43628 -92.65352 32.43383 -92.65417 32.4314 -92.65497 32.429 -92.65591 32.42664 -92.65698 32.42432 -92.65818 32.42205 -92.65952 32.41983 -92.66098 32.41767 -92.66257 32.41557 -92.66428 32.41354 -92.6661 32.41158 -92.66804 32.4097 -92.67008 32.4079 -92.67222 32.40619 -92.67446 32.40457 -92.67679 32.40304 -92.67921 32.40161 -92.68171 32.40029 -92.68428 32.39907 -92.68692 32.39796 -92.68963 32.39695 -92.69238 32.39607 -92.69519 32.39529 -92.69803 32.39464 -92.70091 32.3941 -92.70382 32.39368 -92.70675 32.39339 -92.7097 32.39321 -92.71222 32.39316 -92.71517 32.39323 -92.71811 32.39342 -92.72104 32.39374 -92.72394 32.39417 -92.72682 32.39472 -92.72966 32.3954 -92.73246 32.39619 -92.73521 32.39709 -92.7379 32.39811 -92.74053 32.39924 -92.74309 32.40047 -92.74558 32.40181 -92.74799 32.40326 -92.75031 32.40479 -92.75253 32.40643 -92.75466 32.40815 -92.75669 32.40996 -92.75861 32.41185 -92.76042 32.41382 -92.76211 32.41587 -92.76368 32.41797 -92.76512 32.42015 -92.76644 32.42237 -92.76763 32.42465 -92.76868 32.42698 -92.76959 32.42935 -92.77037 32.43175 -92.77101 32.43418 -92.7715 32.43664 -92.77185 32.43911 -92.77206 32.44159 -92.77212 32.44408 -92.77204 32.44657 -92.77181 32.44906 -92.77144 32.45153 -92.77092 32.45398 -92.77027 32.4564 -92.76947 32.4588 -92.76853 32.46116 -92.76746 32.46348 -92.76626 32.46575 -92.76492 32.46797 -92.76346 32.47014 -92.76187 32.47223 -92.76016 32.47426 -92.75834 32.47622 -92.7564 32.4781 -92.75436 32.4799 -92.75222 32.48161 -92.74998 32.48322 -92.74765 32.48475 -92.74523 32.48617 -92.74273 32.4875 -92.74016 32.48872 -92.73752 32.48983 -92.73481 32.49083 -92.73206 32.49172 -92.72925 32.49249 -92.72641 32.49314 -92.72353 32.49368 -92.72062 32.4941 -92.71769 32.49439 -92.71474 32.49457 -92.71222 32.49462</ns1:posList>
                                                        </ns1:LinearRing>
                                                    </ns1:interior>
                                                    <ns1:interior>
                                                        <ns1:LinearRing>
                                                            <ns1:posList>-92.07056 32.14677 -92.0735 32.14684 -92.07643 32.14703 -92.07935 32.14735 -92.08225 32.14778 -92.08512 32.14834 -92.08795 32.14901 -92.09074 32.1498 -92.09348 32.1507 -92.09617 32.15172 -92.09879 32.15285 -92.10135 32.15409 -92.10383 32.15543 -92.10623 32.15687 -92.10854 32.15841 -92.11076 32.16004 -92.11289 32.16177 -92.11491 32.16358 -92.11682 32.16547 -92.11862 32.16744 -92.12031 32.16948 -92.12187 32.17159 -92.12331 32.17376 -92.12463 32.17599 -92.12581 32.17827 -92.12686 32.1806 -92.12777 32.18296 -92.12855 32.18537 -92.12918 32.1878 -92.12967 32.19025 -92.13002 32.19273 -92.13023 32.19521 -92.13029 32.1977 -92.13021 32.20019 -92.12998 32.20267 -92.12961 32.20514 -92.12909 32.20759 -92.12844 32.21002 -92.12764 32.21242 -92.12671 32.21478 -92.12564 32.2171 -92.12444 32.21937 -92.12311 32.22159 -92.12165 32.22375 -92.12006 32.22585 -92.11836 32.22788 -92.11654 32.22983 -92.11461 32.23171 -92.11258 32.23351 -92.11044 32.23522 -92.1082 32.23684 -92.10588 32.23836 -92.10346 32.23979 -92.10097 32.24111 -92.09841 32.24233 -92.09577 32.24344 -92.09308 32.24444 -92.09033 32.24533 -92.08753 32.2461 -92.08469 32.24676 -92.08182 32.24729 -92.07892 32.24771 -92.076 32.248 -92.07306 32.24818 -92.07056 32.24823 -92.06762 32.24816 -92.06468 32.24797 -92.06177 32.24766 -92.05887 32.24722 -92.056 32.24667 -92.05317 32.246 -92.05038 32.24521 -92.04763 32.2443 -92.04495 32.24329 -92.04232 32.24216 -92.03977 32.24093 -92.03729 32.23959 -92.03489 32.23815 -92.03258 32.23661 -92.03035 32.23498 -92.02823 32.23325 -92.02621 32.23144 -92.0243 32.22955 -92.02249 32.22759 -92.02081 32.22555 -92.01924 32.22344 -92.0178 32.22127 -92.01649 32.21904 -92.0153 32.21676 -92.01425 32.21444 -92.01334 32.21207 -92.01257 32.20967 -92.01193 32.20724 -92.01144 32.20478 -92.01109 32.20231 -92.01088 32.19983 -92.01082 32.19734 -92.0109 32.19485 -92.01113 32.19237 -92.0115 32.18989 -92.01201 32.18744 -92.01267 32.18501 -92.01346 32.18262 -92.0144 32.18026 -92.01546 32.17793 -92.01667 32.17566 -92.018 32.17344 -92.01946 32.17128 -92.02104 32.16918 -92.02274 32.16715 -92.02456 32.16519 -92.02649 32.16331 -92.02853 32.16151 -92.03067 32.1598 -92.0329 32.15818 -92.03523 32.15665 -92.03764 32.15523 -92.04013 32.1539 -92.04269 32.15268 -92.04533 32.15157 -92.04802 32.15057 -92.05077 32.14968 -92.05357 32.1489 -92.05641 32.14825 -92.05928 32.14771 -92.06218 32.14729 -92.0651 32.147 -92.06804 32.14682 -92.07056 32.14677</ns1:posList>
                                                        </ns1:LinearRing>
                                                    </ns1:interior>
                                                    <ns1:interior>
                                                        <ns1:LinearRing>
                                                            <ns1:posList>-92.17619 32.1459 -92.17325 32.14583 -92.17032 32.14564 -92.1674 32.14532 -92.16451 32.14489 -92.16164 32.14434 -92.15881 32.14366 -92.15603 32.14287 -92.15329 32.14197 -92.15061 32.14095 -92.14798 32.13983 -92.14543 32.13859 -92.14295 32.13725 -92.14056 32.13581 -92.13825 32.13427 -92.13603 32.13264 -92.13391 32.13092 -92.13189 32.12911 -92.12998 32.12722 -92.12818 32.12525 -92.12649 32.12321 -92.12493 32.1211 -92.12349 32.11893 -92.12218 32.1167 -92.121 32.11442 -92.11995 32.1121 -92.11904 32.10973 -92.11826 32.10733 -92.11763 32.1049 -92.11714 32.10244 -92.11679 32.09997 -92.11658 32.09748 -92.11652 32.09499 -92.1166 32.0925 -92.11683 32.09002 -92.1172 32.08755 -92.11771 32.0851 -92.11837 32.08267 -92.11916 32.08027 -92.12009 32.07791 -92.12116 32.07559 -92.12236 32.07332 -92.12369 32.0711 -92.12515 32.06893 -92.12673 32.06683 -92.12844 32.0648 -92.13025 32.06284 -92.13218 32.06096 -92.13422 32.05917 -92.13635 32.05745 -92.13858 32.05583 -92.14091 32.05431 -92.14332 32.05288 -92.14581 32.05156 -92.14837 32.05034 -92.151 32.04922 -92.15369 32.04822 -92.15644 32.04734 -92.15923 32.04656 -92.16207 32.04591 -92.16494 32.04537 -92.16784 32.04495 -92.17076 32.04466 -92.17369 32.04448 -92.17619 32.04443 -92.17913 32.0445 -92.18206 32.04469 -92.18498 32.04501 -92.18787 32.04544 -92.19074 32.04599 -92.19357 32.04667 -92.19635 32.04746 -92.19909 32.04836 -92.20178 32.04938 -92.2044 32.05051 -92.20695 32.05174 -92.20943 32.05308 -92.21182 32.05452 -92.21414 32.05606 -92.21635 32.0577 -92.21848 32.05942 -92.2205 32.06123 -92.22241 32.06312 -92.22421 32.06509 -92.22589 32.06713 -92.22746 32.06924 -92.2289 32.07142 -92.23021 32.07364 -92.23139 32.07592 -92.23244 32.07825 -92.23335 32.08062 -92.23413 32.08302 -92.23476 32.08545 -92.23525 32.08791 -92.2356 32.09038 -92.23581 32.09287 -92.23587 32.09536 -92.23579 32.09784 -92.23556 32.10033 -92.23519 32.1028 -92.23468 32.10525 -92.23402 32.10768 -92.23323 32.11007 -92.2323 32.11244 -92.23123 32.11476 -92.23003 32.11703 -92.2287 32.11925 -92.22724 32.12141 -92.22566 32.12351 -92.22396 32.12554 -92.22214 32.1275 -92.22022 32.12937 -92.21818 32.13117 -92.21605 32.13288 -92.21381 32.1345 -92.21149 32.13603 -92.20908 32.13745 -92.20659 32.13878 -92.20403 32.14 -92.2014 32.14111 -92.19871 32.14211 -92.19596 32.143 -92.19317 32.14377 -92.19033 32.14442 -92.18746 32.14496 -92.18456 32.14538 -92.18164 32.14567 -92.17871 32.14585 -92.17619 32.1459</ns1:posList>
                                                        </ns1:LinearRing>
                                                    </ns1:interior>
                                                </ns1:PolygonPatch>
                                            </ns1:patches>
                                        </ns3:Surface>
                                    </ns3:horizontalProjection>
                                </ns3:AirspaceVolume>
                            </ns3:theAirspaceVolume>
                        </ns3:AirspaceGeometryComponent>
                    </ns3:geometryComponent>
                </ns3:AirspaceTimeSlice>
            </ns3:timeSlice>
        </ns3:Airspace>
    </ns8:hasMember>
    <ns8:hasMember ns2:type="simple">
        <ns3:Airspace ns1:id="19336115">
            <ns1:description ns2:type="simple">MINIMUM VECTORING ALTITUDE (MVA)</ns1:description>
            <ns1:boundedBy xsi:nil="true" xmlns:xsi="http://www.w3.org/2001/XMLSchema-instance"/>
            <ns3:timeSlice>
                <ns3:AirspaceTimeSlice>
                    <ns1:validTime ns2:type="simple">
                        <ns1:TimePeriod>
                            <ns1:beginPosition>1980-01-01T14:00:00Z</ns1:beginPosition>
                            <ns1:endPosition indeterminatePosition="unknown"/>
                        </ns1:TimePeriod>
                    </ns1:validTime>
                    <ns3:interpretation>BASELINE</ns3:interpretation>
                    <ns3:sequenceNumber>1</ns3:sequenceNumber>
                    <ns3:type>OTHER</ns3:type>
                    <ns3:designator xsi:nil="true" xmlns:xsi="http://www.w3.org/2001/XMLSchema-instance"/>
                    <ns3:localType xsi:nil="true" xmlns:xsi="http://www.w3.org/2001/XMLSchema-instance"/>
                    <ns3:name>B</ns3:name>
                    <ns3:designatorICAO xsi:nil="true" xmlns:xsi="http://www.w3.org/2001/XMLSchema-instance"/>
                    <ns3:controlType xsi:nil="true" xmlns:xsi="http://www.w3.org/2001/XMLSchema-instance"/>
                    <ns3:upperLowerSeparation xsi:nil="true" xmlns:xsi="http://www.w3.org/2001/XMLSchema-instance"/>
                    <ns3:protectedRoute xsi:nil="true" xmlns:xsi="http://www.w3.org/2001/XMLSchema-instance"/>
                    <ns3:geometryComponent>
                        <ns3:AirspaceGeometryComponent>
                            <ns3:operation xsi:nil="true" xmlns:xsi="http://www.w3.org/2001/XMLSchema-instance"/>
                            <ns3:operationSequence xsi:nil="true" xmlns:xsi="http://www.w3.org/2001/XMLSchema-instance"/>
                            <ns3:theAirspaceVolume>
                                <ns3:AirspaceVolume>
                                    <ns3:minimumLimit uom="FT">2700</ns3:minimumLimit>
                                    <ns3:minimumLimitReference>MSL</ns3:minimumLimitReference>
                                    <ns3:horizontalProjection>
                                        <ns3:Surface srsName="urn:ogc:def:crs:OGC:1.3:CRS84" ns1:id="4f87c142-5ef4-4bb9-a0f6-0baeebc2f2b6">
                                            <ns1:patches>
                                                <ns1:PolygonPatch interpolation="planar">
                                                    <ns1:exterior>
                                                        <ns1:LinearRing>
                                                            <ns1:posList>-90.83141 32.50609 -90.83334 32.45703 -90.83812 32.40809 -90.84574 32.35938 -90.85618 32.31101 -90.86942 32.26311 -90.88542 32.2158 -90.90415 32.16918 -90.92555 32.12337 -90.94959 32.07848 -90.9762 32.03463 -91.00531 31.99191 -91.03686 31.95044 -91.07078 31.91031 -91.10697 31.87163 -91.14535 31.83448 -91.18583 31.79897 -91.22832 31.76518 -91.2727 31.73318 -91.31888 31.70307 -91.36674 31.67491 -91.41616 31.64878 -91.46703 31.62473 -91.51923 31.60283 -91.57262 31.58314 -91.62709 31.5657 -91.68249 31.55055 -91.7387 31.53774 -91.79558 31.52729 -91.85299 31.51923 -91.9108 31.51359 -91.96886 31.51036 -92.01394 31.50954 -92.0721 31.51088 -92.13012 31.51465 -92.18785 31.52084 -92.24515 31.52944 -92.30189 31.54042 -92.35793 31.55376 -92.41314 31.56943 -92.46737 31.58738 -92.52051 31.60758 -92.57242 31.62996 -92.62297 31.65448 -92.67206 31.68108 -92.71954 31.70968 -92.76533 31.74023 -92.80929 31.77264 -92.85133 31.80682 -92.89135 31.84271 -92.92925 31.88021 -92.96494 31.91923 -92.99832 31.95967 -93.02933 32.00143 -93.05789 32.04441 -93.08392 32.08851 -93.10737 32.13361 -93.12818 32.17961 -93.1463 32.2264 -93.16168 32.27386 -93.17429 32.32187 -93.18409 32.37033 -93.19108 32.4191 -93.19521 32.46808 -93.19646 32.50609 -93.19581 32.55515 -93.19232 32.60409 -93.18597 32.6528 -93.17679 32.70117 -93.16481 32.74907 -93.15005 32.7964 -93.13254 32.84303 -93.11233 32.88886 -93.08947 32.93378 -93.06401 32.97769 -93.03601 33.02047 -93.00554 33.06203 -92.97268 33.10226 -92.9375 33.14108 -92.90009 33.17839 -92.86054 33.2141 -92.81894 33.24814 -92.77539 33.28041 -92.73001 33.31085 -92.68289 33.33937 -92.63415 33.36593 -92.58391 33.39044 -92.53229 33.41287 -92.47942 33.43314 -92.42542 33.45123 -92.37042 33.46707 -92.31455 33.48065 -92.25795 33.49192 -92.20076 33.50085 -92.14311 33.50744 -92.08514 33.51166 -92.02699 33.5135 -92.01394 33.51359 -91.95577 33.51228 -91.89775 33.50859 -91.84002 33.50254 -91.78271 33.49413 -91.72597 33.48338 -91.66993 33.47032 -91.61472 33.45498 -91.56048 33.4374 -91.50734 33.41761 -91.45543 33.39566 -91.40487 33.37161 -91.35579 33.34551 -91.3083 33.31742 -91.26251 33.28741 -91.21854 33.25554 -91.1765 33.22189 -91.13648 33.18655 -91.09858 33.14959 -91.06289 33.1111 -91.0295 33.07118 -90.99849 33.02991 -90.96993 32.98739 -90.9439 32.94373 -90.92044 32.89903 -90.89963 32.85339 -90.88152 32.80693 -90.86613 32.75975 -90.85352 32.71197 -90.84371 32.6637 -90.83673 32.61505 -90.83259 32.56615 -90.83131 32.51711 -90.83141 32.50609</ns1:posList>
                                                        </ns1:LinearRing>
                                                    </ns1:exterior>
                                                    <ns1:interior>
                                                        <ns1:LinearRing>
                                                            <ns1:posList>-92.018 31.84283 -91.97921 31.84349 -91.9405 31.84576 -91.90198 31.84965 -91.86372 31.85514 -91.82583 31.86221 -91.78839 31.87086 -91.75149 31.88105 -91.71523 31.89277 -91.67969 31.90598 -91.64496 31.92065 -91.61111 31.93675 -91.57824 31.95424 -91.54642 31.97307 -91.51572 31.9932 -91.48623 32.01458 -91.45801 32.03715 -91.43113 32.06086 -91.40566 32.08566 -91.38165 32.11148 -91.35916 32.13826 -91.33826 32.16593 -91.31898 32.19443 -91.30138 32.22368 -91.2855 32.25362 -91.27137 32.28417 -91.25903 32.31527 -91.24852 32.34682 -91.23984 32.37877 -91.23304 32.41102 -91.22811 32.4435 -91.22508 32.47614 -91.22396 32.50885 -91.22473 32.54156 -91.22741 32.57418 -91.23199 32.60664 -91.23845 32.63886 -91.24677 32.67076 -91.25695 32.70227 -91.26896 32.73332 -91.28276 32.76381 -91.29832 32.79369 -91.3156 32.82289 -91.33457 32.85132 -91.35518 32.87894 -91.37738 32.90566 -91.40111 32.93142 -91.42632 32.95617 -91.45294 32.97985 -91.48092 33.00239 -91.51018 33.02376 -91.54066 33.04388 -91.57228 33.06273 -91.60496 33.08025 -91.63864 33.0964 -91.67321 33.11114 -91.70861 33.12444 -91.74474 33.13628 -91.78153 33.14661 -91.81887 33.15541 -91.85669 33.16267 -91.89489 33.16837 -91.93337 33.17249 -91.97205 33.17503 -92.01083 33.17597 -92.018 33.17597 -92.05679 33.17517 -92.09548 33.17278 -92.13398 33.16881 -92.17221 33.16325 -92.21007 33.15614 -92.24746 33.14747 -92.2843 33.13728 -92.32049 33.12559 -92.35596 33.11242 -92.39062 33.09781 -92.42437 33.08178 -92.45715 33.06439 -92.48887 33.04566 -92.51946 33.02565 -92.54884 33.0044 -92.57693 32.98196 -92.60369 32.95839 -92.62903 32.93373 -92.6529 32.90806 -92.67523 32.88142 -92.69599 32.85389 -92.71511 32.82553 -92.73256 32.7964 -92.74828 32.76658 -92.76224 32.73614 -92.77441 32.70514 -92.78476 32.67367 -92.79326 32.6418 -92.79989 32.60961 -92.80464 32.57717 -92.80749 32.54456 -92.80844 32.51185 -92.80749 32.47914 -92.80463 32.44649 -92.79988 32.41399 -92.79325 32.38172 -92.78475 32.34974 -92.7744 32.31815 -92.76223 32.28701 -92.74826 32.25641 -92.73254 32.22641 -92.71509 32.19709 -92.69597 32.16851 -92.67521 32.14076 -92.65287 32.1139 -92.629 32.08799 -92.60366 32.0631 -92.57691 32.03928 -92.54881 32.0166 -92.51943 31.99512 -92.48884 31.97487 -92.45712 31.95592 -92.42434 31.93831 -92.39058 31.92208 -92.35593 31.90727 -92.32046 31.89392 -92.28426 31.88207 -92.24742 31.87173 -92.21003 31.86295 -92.17217 31.85573 -92.13395 31.8501 -92.09544 31.84606 -92.05675 31.84364 -92.018 31.84283</ns1:posList>
                                                        </ns1:LinearRing>
                                                    </ns1:interior>
                                                </ns1:PolygonPatch>
                                            </ns1:patches>
                                        </ns3:Surface>
                                    </ns3:horizontalProjection>
                                </ns3:AirspaceVolume>
                            </ns3:theAirspaceVolume>
                        </ns3:AirspaceGeometryComponent>
                    </ns3:geometryComponent>
                </ns3:AirspaceTimeSlice>
            </ns3:timeSlice>
        </ns3:Airspace>
    </ns8:hasMember>
    <ns8:hasMember ns2:type="simple">
        <ns3:Airspace ns1:id="19336116">
            <ns1:description ns2:type="simple">MINIMUM VECTORING ALTITUDE (MVA)</ns1:description>
            <ns1:boundedBy xsi:nil="true" xmlns:xsi="http://www.w3.org/2001/XMLSchema-instance"/>
            <ns3:timeSlice>
                <ns3:AirspaceTimeSlice>
                    <ns1:validTime ns2:type="simple">
                        <ns1:TimePeriod>
                            <ns1:beginPosition>1980-01-01T14:00:00Z</ns1:beginPosition>
                            <ns1:endPosition indeterminatePosition="unknown"/>
                        </ns1:TimePeriod>
                    </ns1:validTime>
                    <ns3:interpretation>BASELINE</ns3:interpretation>
                    <ns3:sequenceNumber>1</ns3:sequenceNumber>
                    <ns3:type>OTHER</ns3:type>
                    <ns3:designator xsi:nil="true" xmlns:xsi="http://www.w3.org/2001/XMLSchema-instance"/>
                    <ns3:localType xsi:nil="true" xmlns:xsi="http://www.w3.org/2001/XMLSchema-instance"/>
                    <ns3:name>C</ns3:name>
                    <ns3:designatorICAO xsi:nil="true" xmlns:xsi="http://www.w3.org/2001/XMLSchema-instance"/>
                    <ns3:controlType xsi:nil="true" xmlns:xsi="http://www.w3.org/2001/XMLSchema-instance"/>
                    <ns3:upperLowerSeparation xsi:nil="true" xmlns:xsi="http://www.w3.org/2001/XMLSchema-instance"/>
                    <ns3:protectedRoute xsi:nil="true" xmlns:xsi="http://www.w3.org/2001/XMLSchema-instance"/>
                    <ns3:geometryComponent>
                        <ns3:AirspaceGeometryComponent>
                            <ns3:operation xsi:nil="true" xmlns:xsi="http://www.w3.org/2001/XMLSchema-instance"/>
                            <ns3:operationSequence xsi:nil="true" xmlns:xsi="http://www.w3.org/2001/XMLSchema-instance"/>
                            <ns3:theAirspaceVolume>
                                <ns3:AirspaceVolume>
                                    <ns3:minimumLimit uom="FT">2100</ns3:minimumLimit>
                                    <ns3:minimumLimitReference>MSL</ns3:minimumLimitReference>
                                    <ns3:horizontalProjection>
                                        <ns3:Surface srsName="urn:ogc:def:crs:OGC:1.3:CRS84" ns1:id="b7639814-cc37-4e50-86bf-139cb814d433">
                                            <ns1:patches>
                                                <ns1:PolygonPatch interpolation="planar">
                                                    <ns1:exterior>
                                                        <ns1:LinearRing>
                                                            <ns1:posList>-92.03835 32.62858 -92.03658 32.63058 -92.03492 32.63264 -92.03339 32.63477 -92.03199 32.63697 -92.03071 32.63922 -92.02957 32.64151 -92.02856 32.64386 -92.02769 32.64624 -92.02696 32.64865 -92.02637 32.6511 -92.02593 32.65356 -92.02562 32.65604 -92.02547 32.65853 -92.02545 32.66102 -92.02559 32.66351 -92.02587 32.66599 -92.02629 32.66845 -92.02686 32.6709 -92.02756 32.67332 -92.02841 32.6757 -92.0294 32.67805 -92.03052 32.68036 -92.03177 32.68261 -92.03316 32.68481 -92.03467 32.68695 -92.0363 32.68903 -92.03806 32.69104 -92.03914 32.69218 -92.04107 32.69408 -92.04312 32.69589 -92.04526 32.69762 -92.04751 32.69925 -92.04984 32.70079 -92.05227 32.70224 -92.05477 32.70358 -92.05735 32.70481 -92.06 32.70594 -92.06271 32.70696 -92.06548 32.70786 -92.06829 32.70865 -92.07115 32.70932 -92.07405 32.70988 -92.07697 32.71031 -92.07992 32.71062 -92.08288 32.71081 -92.08585 32.71088 -92.08881 32.71082 -92.09177 32.71064 -92.09472 32.71034 -92.09765 32.70992 -92.10055 32.70938 -92.10341 32.70872 -92.10623 32.70794 -92.109 32.70705 -92.11172 32.70604 -92.11437 32.70492 -92.11696 32.70369 -92.11947 32.70236 -92.1219 32.70093 -92.12425 32.6994 -92.1265 32.69777 -92.12865 32.69605 -92.13071 32.69424 -92.13265 32.69236 -92.13448 32.69039 -92.1362 32.68835 -92.13779 32.68624 -92.13926 32.68407 -92.1406 32.68184 -92.14181 32.67956 -92.14288 32.67723 -92.14382 32.67486 -92.14462 32.67245 -92.14528 32.67001 -92.14579 32.66755 -92.14616 32.66507 -92.14639 32.66258 -92.14646 32.66008 -92.1464 32.65758 -92.14619 32.65509 -92.14583 32.65261 -92.14533 32.65015 -92.14468 32.64771 -92.1439 32.6453 -92.14297 32.64292 -92.14191 32.64059 -92.14072 32.6383 -92.13939 32.63606 -92.13793 32.63388 -92.13635 32.63177 -92.13464 32.62972 -92.13282 32.62775 -92.13089 32.62585 -92.12884 32.62404 -92.1267 32.62231 -92.12446 32.62067 -92.12212 32.61913 -92.1197 32.61768 -92.11719 32.61634 -92.11461 32.6151 -92.11196 32.61397 -92.10925 32.61296 -92.10648 32.61205 -92.10367 32.61126 -92.10081 32.61059 -92.09791 32.61004 -92.09499 32.6096 -92.09204 32.60929 -92.08908 32.6091 -92.08612 32.60903 -92.08315 32.60909 -92.08019 32.60927 -92.07724 32.60957 -92.07431 32.60999 -92.07141 32.61053 -92.06855 32.6112 -92.06573 32.61197 -92.06296 32.61287 -92.06024 32.61388 -92.05759 32.615 -92.055 32.61622 -92.05249 32.61756 -92.05006 32.61899 -92.04771 32.62053 -92.04546 32.62216 -92.04331 32.62388 -92.04126 32.62568 -92.03931 32.62757 -92.03835 32.62858</ns1:posList>
                                                        </ns1:LinearRing>
                                                    </ns1:exterior>
                                                </ns1:PolygonPatch>
                                            </ns1:patches>
                                        </ns3:Surface>
                                    </ns3:horizontalProjection>
                                </ns3:AirspaceVolume>
                            </ns3:theAirspaceVolume>
                        </ns3:AirspaceGeometryComponent>
                    </ns3:geometryComponent>
                </ns3:AirspaceTimeSlice>
            </ns3:timeSlice>
        </ns3:Airspace>
    </ns8:hasMember>
    <ns8:hasMember ns2:type="simple">
        <ns3:Airspace ns1:id="19336120">
            <ns1:description ns2:type="simple">MINIMUM VECTORING ALTITUDE (MVA)</ns1:description>
            <ns1:boundedBy xsi:nil="true" xmlns:xsi="http://www.w3.org/2001/XMLSchema-instance"/>
            <ns3:timeSlice>
                <ns3:AirspaceTimeSlice>
                    <ns1:validTime ns2:type="simple">
                        <ns1:TimePeriod>
                            <ns1:beginPosition>1980-01-01T14:00:00Z</ns1:beginPosition>
                            <ns1:endPosition indeterminatePosition="unknown"/>
                        </ns1:TimePeriod>
                    </ns1:validTime>
                    <ns3:interpretation>BASELINE</ns3:interpretation>
                    <ns3:sequenceNumber>1</ns3:sequenceNumber>
                    <ns3:type>OTHER</ns3:type>
                    <ns3:designator xsi:nil="true" xmlns:xsi="http://www.w3.org/2001/XMLSchema-instance"/>
                    <ns3:localType xsi:nil="true" xmlns:xsi="http://www.w3.org/2001/XMLSchema-instance"/>
                    <ns3:name>D</ns3:name>
                    <ns3:designatorICAO xsi:nil="true" xmlns:xsi="http://www.w3.org/2001/XMLSchema-instance"/>
                    <ns3:controlType xsi:nil="true" xmlns:xsi="http://www.w3.org/2001/XMLSchema-instance"/>
                    <ns3:upperLowerSeparation xsi:nil="true" xmlns:xsi="http://www.w3.org/2001/XMLSchema-instance"/>
                    <ns3:protectedRoute xsi:nil="true" xmlns:xsi="http://www.w3.org/2001/XMLSchema-instance"/>
                    <ns3:geometryComponent>
                        <ns3:AirspaceGeometryComponent>
                            <ns3:operation xsi:nil="true" xmlns:xsi="http://www.w3.org/2001/XMLSchema-instance"/>
                            <ns3:operationSequence xsi:nil="true" xmlns:xsi="http://www.w3.org/2001/XMLSchema-instance"/>
                            <ns3:theAirspaceVolume>
                                <ns3:AirspaceVolume>
                                    <ns3:minimumLimit uom="FT">3000</ns3:minimumLimit>
                                    <ns3:minimumLimitReference>MSL</ns3:minimumLimitReference>
                                    <ns3:horizontalProjection>
                                        <ns3:Surface srsName="urn:ogc:def:crs:OGC:1.3:CRS84" ns1:id="994ccd7f-009b-4402-9d0c-1a82effe30f2">
                                            <ns1:patches>
                                                <ns1:PolygonPatch interpolation="planar">
                                                    <ns1:exterior>
                                                        <ns1:LinearRing>
                                                            <ns1:posList>-92.07056 32.14677 -92.0735 32.14684 -92.07643 32.14703 -92.07935 32.14735 -92.08225 32.14778 -92.08512 32.14834 -92.08795 32.14901 -92.09074 32.1498 -92.09348 32.1507 -92.09617 32.15172 -92.09879 32.15285 -92.10135 32.15409 -92.10383 32.15543 -92.10623 32.15687 -92.10854 32.15841 -92.11076 32.16004 -92.11289 32.16177 -92.11491 32.16358 -92.11682 32.16547 -92.11862 32.16744 -92.12031 32.16948 -92.12187 32.17159 -92.12331 32.17376 -92.12463 32.17599 -92.12581 32.17827 -92.12686 32.1806 -92.12777 32.18296 -92.12855 32.18537 -92.12918 32.1878 -92.12967 32.19025 -92.13002 32.19273 -92.13023 32.19521 -92.13029 32.1977 -92.13021 32.20019 -92.12998 32.20267 -92.12961 32.20514 -92.12909 32.20759 -92.12844 32.21002 -92.12764 32.21242 -92.12671 32.21478 -92.12564 32.2171 -92.12444 32.21937 -92.12311 32.22159 -92.12165 32.22375 -92.12006 32.22585 -92.11836 32.22788 -92.11654 32.22983 -92.11461 32.23171 -92.11258 32.23351 -92.11044 32.23522 -92.1082 32.23684 -92.10588 32.23836 -92.10346 32.23979 -92.10097 32.24111 -92.09841 32.24233 -92.09577 32.24344 -92.09308 32.24444 -92.09033 32.24533 -92.08753 32.2461 -92.08469 32.24676 -92.08182 32.24729 -92.07892 32.24771 -92.076 32.248 -92.07306 32.24818 -92.07056 32.24823 -92.06762 32.24816 -92.06468 32.24797 -92.06177 32.24766 -92.05887 32.24722 -92.056 32.24667 -92.05317 32.246 -92.05038 32.24521 -92.04763 32.2443 -92.04495 32.24329 -92.04232 32.24216 -92.03977 32.24093 -92.03729 32.23959 -92.03489 32.23815 -92.03258 32.23661 -92.03035 32.23498 -92.02823 32.23325 -92.02621 32.23144 -92.0243 32.22955 -92.02249 32.22759 -92.02081 32.22555 -92.01924 32.22344 -92.0178 32.22127 -92.01649 32.21904 -92.0153 32.21676 -92.01425 32.21444 -92.01334 32.21207 -92.01257 32.20967 -92.01193 32.20724 -92.01144 32.20478 -92.01109 32.20231 -92.01088 32.19983 -92.01082 32.19734 -92.0109 32.19485 -92.01113 32.19237 -92.0115 32.18989 -92.01201 32.18744 -92.01267 32.18501 -92.01346 32.18262 -92.0144 32.18026 -92.01546 32.17793 -92.01667 32.17566 -92.018 32.17344 -92.01946 32.17128 -92.02104 32.16918 -92.02274 32.16715 -92.02456 32.16519 -92.02649 32.16331 -92.02853 32.16151 -92.03067 32.1598 -92.0329 32.15818 -92.03523 32.15665 -92.03764 32.15523 -92.04013 32.1539 -92.04269 32.15268 -92.04533 32.15157 -92.04802 32.15057 -92.05077 32.14968 -92.05357 32.1489 -92.05641 32.14825 -92.05928 32.14771 -92.06218 32.14729 -92.0651 32.147 -92.06804 32.14682 -92.07056 32.14677</ns1:posList>
                                                        </ns1:LinearRing>
                                                    </ns1:exterior>
                                                </ns1:PolygonPatch>
                                            </ns1:patches>
                                        </ns3:Surface>
                                    </ns3:horizontalProjection>
                                </ns3:AirspaceVolume>
                            </ns3:theAirspaceVolume>
                        </ns3:AirspaceGeometryComponent>
                    </ns3:geometryComponent>
                </ns3:AirspaceTimeSlice>
            </ns3:timeSlice>
        </ns3:Airspace>
    </ns8:hasMember>
    <ns8:hasMember ns2:type="simple">
        <ns3:Airspace ns1:id="19336118">
            <ns1:description ns2:type="simple">MINIMUM VECTORING ALTITUDE (MVA)</ns1:description>
            <ns1:boundedBy xsi:nil="true" xmlns:xsi="http://www.w3.org/2001/XMLSchema-instance"/>
            <ns3:timeSlice>
                <ns3:AirspaceTimeSlice>
                    <ns1:validTime ns2:type="simple">
                        <ns1:TimePeriod>
                            <ns1:beginPosition>1980-01-01T14:00:00Z</ns1:beginPosition>
                            <ns1:endPosition indeterminatePosition="unknown"/>
                        </ns1:TimePeriod>
                    </ns1:validTime>
                    <ns3:interpretation>BASELINE</ns3:interpretation>
                    <ns3:sequenceNumber>1</ns3:sequenceNumber>
                    <ns3:type>OTHER</ns3:type>
                    <ns3:designator xsi:nil="true" xmlns:xsi="http://www.w3.org/2001/XMLSchema-instance"/>
                    <ns3:localType xsi:nil="true" xmlns:xsi="http://www.w3.org/2001/XMLSchema-instance"/>
                    <ns3:name>E</ns3:name>
                    <ns3:designatorICAO xsi:nil="true" xmlns:xsi="http://www.w3.org/2001/XMLSchema-instance"/>
                    <ns3:controlType xsi:nil="true" xmlns:xsi="http://www.w3.org/2001/XMLSchema-instance"/>
                    <ns3:upperLowerSeparation xsi:nil="true" xmlns:xsi="http://www.w3.org/2001/XMLSchema-instance"/>
                    <ns3:protectedRoute xsi:nil="true" xmlns:xsi="http://www.w3.org/2001/XMLSchema-instance"/>
                    <ns3:geometryComponent>
                        <ns3:AirspaceGeometryComponent>
                            <ns3:operation xsi:nil="true" xmlns:xsi="http://www.w3.org/2001/XMLSchema-instance"/>
                            <ns3:operationSequence xsi:nil="true" xmlns:xsi="http://www.w3.org/2001/XMLSchema-instance"/>
                            <ns3:theAirspaceVolume>
                                <ns3:AirspaceVolume>
                                    <ns3:minimumLimit uom="FT">3100</ns3:minimumLimit>
                                    <ns3:minimumLimitReference>MSL</ns3:minimumLimitReference>
                                    <ns3:horizontalProjection>
                                        <ns3:Surface srsName="urn:ogc:def:crs:OGC:1.3:CRS84" ns1:id="aeb43ccd-49f8-492a-a5b3-4a147d4a74de">
                                            <ns1:patches>
                                                <ns1:PolygonPatch interpolation="planar">
                                                    <ns1:exterior>
                                                        <ns1:LinearRing>
                                                            <ns1:posList>-92.17619 32.1459 -92.17325 32.14583 -92.17032 32.14564 -92.1674 32.14532 -92.16451 32.14489 -92.16164 32.14434 -92.15881 32.14366 -92.15603 32.14287 -92.15329 32.14197 -92.15061 32.14095 -92.14798 32.13983 -92.14543 32.13859 -92.14295 32.13725 -92.14056 32.13581 -92.13825 32.13427 -92.13603 32.13264 -92.13391 32.13092 -92.13189 32.12911 -92.12998 32.12722 -92.12818 32.12525 -92.12649 32.12321 -92.12493 32.1211 -92.12349 32.11893 -92.12218 32.1167 -92.121 32.11442 -92.11995 32.1121 -92.11904 32.10973 -92.11826 32.10733 -92.11763 32.1049 -92.11714 32.10244 -92.11679 32.09997 -92.11658 32.09748 -92.11652 32.09499 -92.1166 32.0925 -92.11683 32.09002 -92.1172 32.08755 -92.11771 32.0851 -92.11837 32.08267 -92.11916 32.08027 -92.12009 32.07791 -92.12116 32.07559 -92.12236 32.07332 -92.12369 32.0711 -92.12515 32.06893 -92.12673 32.06683 -92.12844 32.0648 -92.13025 32.06284 -92.13218 32.06096 -92.13422 32.05917 -92.13635 32.05745 -92.13858 32.05583 -92.14091 32.05431 -92.14332 32.05288 -92.14581 32.05156 -92.14837 32.05034 -92.151 32.04922 -92.15369 32.04822 -92.15644 32.04734 -92.15923 32.04656 -92.16207 32.04591 -92.16494 32.04537 -92.16784 32.04495 -92.17076 32.04466 -92.17369 32.04448 -92.17619 32.04443 -92.17913 32.0445 -92.18206 32.04469 -92.18498 32.04501 -92.18787 32.04544 -92.19074 32.04599 -92.19357 32.04667 -92.19635 32.04746 -92.19909 32.04836 -92.20178 32.04938 -92.2044 32.05051 -92.20695 32.05174 -92.20943 32.05308 -92.21182 32.05452 -92.21414 32.05606 -92.21635 32.0577 -92.21848 32.05942 -92.2205 32.06123 -92.22241 32.06312 -92.22421 32.06509 -92.22589 32.06713 -92.22746 32.06924 -92.2289 32.07142 -92.23021 32.07364 -92.23139 32.07592 -92.23244 32.07825 -92.23335 32.08062 -92.23413 32.08302 -92.23476 32.08545 -92.23525 32.08791 -92.2356 32.09038 -92.23581 32.09287 -92.23587 32.09536 -92.23579 32.09784 -92.23556 32.10033 -92.23519 32.1028 -92.23468 32.10525 -92.23402 32.10768 -92.23323 32.11007 -92.2323 32.11244 -92.23123 32.11476 -92.23003 32.11703 -92.2287 32.11925 -92.22724 32.12141 -92.22566 32.12351 -92.22396 32.12554 -92.22214 32.1275 -92.22022 32.12937 -92.21818 32.13117 -92.21605 32.13288 -92.21381 32.1345 -92.21149 32.13603 -92.20908 32.13745 -92.20659 32.13878 -92.20403 32.14 -92.2014 32.14111 -92.19871 32.14211 -92.19596 32.143 -92.19317 32.14377 -92.19033 32.14442 -92.18746 32.14496 -92.18456 32.14538 -92.18164 32.14567 -92.17871 32.14585 -92.17619 32.1459</ns1:posList>
                                                        </ns1:LinearRing>
                                                    </ns1:exterior>
                                                </ns1:PolygonPatch>
                                            </ns1:patches>
                                        </ns3:Surface>
                                    </ns3:horizontalProjection>
                                </ns3:AirspaceVolume>
                            </ns3:theAirspaceVolume>
                        </ns3:AirspaceGeometryComponent>
                    </ns3:geometryComponent>
                </ns3:AirspaceTimeSlice>
            </ns3:timeSlice>
        </ns3:Airspace>
    </ns8:hasMember>
    <ns8:hasMember ns2:type="simple">
        <ns3:Airspace ns1:id="19336114">
            <ns1:description ns2:type="simple">MINIMUM VECTORING ALTITUDE (MVA)</ns1:description>
            <ns1:boundedBy xsi:nil="true" xmlns:xsi="http://www.w3.org/2001/XMLSchema-instance"/>
            <ns3:timeSlice>
                <ns3:AirspaceTimeSlice>
                    <ns1:validTime ns2:type="simple">
                        <ns1:TimePeriod>
                            <ns1:beginPosition>1980-01-01T14:00:00Z</ns1:beginPosition>
                            <ns1:endPosition indeterminatePosition="unknown"/>
                        </ns1:TimePeriod>
                    </ns1:validTime>
                    <ns3:interpretation>BASELINE</ns3:interpretation>
                    <ns3:sequenceNumber>1</ns3:sequenceNumber>
                    <ns3:type>OTHER</ns3:type>
                    <ns3:designator xsi:nil="true" xmlns:xsi="http://www.w3.org/2001/XMLSchema-instance"/>
                    <ns3:localType xsi:nil="true" xmlns:xsi="http://www.w3.org/2001/XMLSchema-instance"/>
                    <ns3:name>F</ns3:name>
                    <ns3:designatorICAO xsi:nil="true" xmlns:xsi="http://www.w3.org/2001/XMLSchema-instance"/>
                    <ns3:controlType xsi:nil="true" xmlns:xsi="http://www.w3.org/2001/XMLSchema-instance"/>
                    <ns3:upperLowerSeparation xsi:nil="true" xmlns:xsi="http://www.w3.org/2001/XMLSchema-instance"/>
                    <ns3:protectedRoute xsi:nil="true" xmlns:xsi="http://www.w3.org/2001/XMLSchema-instance"/>
                    <ns3:geometryComponent>
                        <ns3:AirspaceGeometryComponent>
                            <ns3:operation xsi:nil="true" xmlns:xsi="http://www.w3.org/2001/XMLSchema-instance"/>
                            <ns3:operationSequence xsi:nil="true" xmlns:xsi="http://www.w3.org/2001/XMLSchema-instance"/>
                            <ns3:theAirspaceVolume>
                                <ns3:AirspaceVolume>
                                    <ns3:minimumLimit uom="FT">2400</ns3:minimumLimit>
                                    <ns3:minimumLimitReference>MSL</ns3:minimumLimitReference>
                                    <ns3:horizontalProjection>
                                        <ns3:Surface srsName="urn:ogc:def:crs:OGC:1.3:CRS84" ns1:id="c89d998d-c628-43f3-ac53-34e8f9cd72d7">
                                            <ns1:patches>
                                                <ns1:PolygonPatch interpolation="planar">
                                                    <ns1:exterior>
                                                        <ns1:LinearRing>
                                                            <ns1:posList>-92.71222 32.49462 -92.70927 32.49455 -92.70633 32.49436 -92.7034 32.49404 -92.7005 32.49361 -92.69762 32.49306 -92.69478 32.49238 -92.69198 32.4916 -92.68923 32.49069 -92.68654 32.48968 -92.68391 32.48855 -92.68135 32.48731 -92.67886 32.48598 -92.67645 32.48453 -92.67413 32.483 -92.67191 32.48136 -92.66978 32.47964 -92.66775 32.47783 -92.66583 32.47594 -92.66402 32.47397 -92.66233 32.47193 -92.66076 32.46983 -92.65932 32.46766 -92.658 32.46543 -92.65681 32.46315 -92.65576 32.46082 -92.65485 32.45846 -92.65407 32.45606 -92.65343 32.45362 -92.65294 32.45117 -92.65259 32.4487 -92.65238 32.44621 -92.65232 32.44372 -92.6524 32.44124 -92.65263 32.43875 -92.653 32.43628 -92.65352 32.43383 -92.65417 32.4314 -92.65497 32.429 -92.65591 32.42664 -92.65698 32.42432 -92.65818 32.42205 -92.65952 32.41983 -92.66098 32.41767 -92.66257 32.41557 -92.66428 32.41354 -92.6661 32.41158 -92.66804 32.4097 -92.67008 32.4079 -92.67222 32.40619 -92.67446 32.40457 -92.67679 32.40304 -92.67921 32.40161 -92.68171 32.40029 -92.68428 32.39907 -92.68692 32.39796 -92.68963 32.39695 -92.69238 32.39607 -92.69519 32.39529 -92.69803 32.39464 -92.70091 32.3941 -92.70382 32.39368 -92.70675 32.39339 -92.7097 32.39321 -92.71222 32.39316 -92.71517 32.39323 -92.71811 32.39342 -92.72104 32.39374 -92.72394 32.39417 -92.72682 32.39472 -92.72966 32.3954 -92.73246 32.39619 -92.73521 32.39709 -92.7379 32.39811 -92.74053 32.39924 -92.74309 32.40047 -92.74558 32.40181 -92.74799 32.40326 -92.75031 32.40479 -92.75253 32.40643 -92.75466 32.40815 -92.75669 32.40996 -92.75861 32.41185 -92.76042 32.41382 -92.76211 32.41587 -92.76368 32.41797 -92.76512 32.42015 -92.76644 32.42237 -92.76763 32.42465 -92.76868 32.42698 -92.76959 32.42935 -92.77037 32.43175 -92.77101 32.43418 -92.7715 32.43664 -92.77185 32.43911 -92.77206 32.44159 -92.77212 32.44408 -92.77204 32.44657 -92.77181 32.44906 -92.77144 32.45153 -92.77092 32.45398 -92.77027 32.4564 -92.76947 32.4588 -92.76853 32.46116 -92.76746 32.46348 -92.76626 32.46575 -92.76492 32.46797 -92.76346 32.47014 -92.76187 32.47223 -92.76016 32.47426 -92.75834 32.47622 -92.7564 32.4781 -92.75436 32.4799 -92.75222 32.48161 -92.74998 32.48322 -92.74765 32.48475 -92.74523 32.48617 -92.74273 32.4875 -92.74016 32.48872 -92.73752 32.48983 -92.73481 32.49083 -92.73206 32.49172 -92.72925 32.49249 -92.72641 32.49314 -92.72353 32.49368 -92.72062 32.4941 -92.71769 32.49439 -92.71474 32.49457 -92.71222 32.49462</ns1:posList>
                                                        </ns1:LinearRing>
                                                    </ns1:exterior>
                                                </ns1:PolygonPatch>
                                            </ns1:patches>
                                        </ns3:Surface>
                                    </ns3:horizontalProjection>
                                </ns3:AirspaceVolume>
                            </ns3:theAirspaceVolume>
                        </ns3:AirspaceGeometryComponent>
                    </ns3:geometryComponent>
                </ns3:AirspaceTimeSlice>
            </ns3:timeSlice>
        </ns3:Airspace>
    </ns8:hasMember>
    <ns8:hasMember ns2:type="simple">
        <ns3:Airspace ns1:id="19336113">
            <ns1:description ns2:type="simple">MINIMUM VECTORING ALTITUDE (MVA)</ns1:description>
            <ns1:boundedBy xsi:nil="true" xmlns:xsi="http://www.w3.org/2001/XMLSchema-instance"/>
            <ns3:timeSlice>
                <ns3:AirspaceTimeSlice>
                    <ns1:validTime ns2:type="simple">
                        <ns1:TimePeriod>
                            <ns1:beginPosition>1980-01-01T14:00:00Z</ns1:beginPosition>
                            <ns1:endPosition indeterminatePosition="unknown"/>
                        </ns1:TimePeriod>
                    </ns1:validTime>
                    <ns3:interpretation>BASELINE</ns3:interpretation>
                    <ns3:sequenceNumber>1</ns3:sequenceNumber>
                    <ns3:type>OTHER</ns3:type>
                    <ns3:designator xsi:nil="true" xmlns:xsi="http://www.w3.org/2001/XMLSchema-instance"/>
                    <ns3:localType xsi:nil="true" xmlns:xsi="http://www.w3.org/2001/XMLSchema-instance"/>
                    <ns3:name>G</ns3:name>
                    <ns3:designatorICAO xsi:nil="true" xmlns:xsi="http://www.w3.org/2001/XMLSchema-instance"/>
                    <ns3:controlType xsi:nil="true" xmlns:xsi="http://www.w3.org/2001/XMLSchema-instance"/>
                    <ns3:upperLowerSeparation xsi:nil="true" xmlns:xsi="http://www.w3.org/2001/XMLSchema-instance"/>
                    <ns3:protectedRoute xsi:nil="true" xmlns:xsi="http://www.w3.org/2001/XMLSchema-instance"/>
                    <ns3:geometryComponent>
                        <ns3:AirspaceGeometryComponent>
                            <ns3:operation xsi:nil="true" xmlns:xsi="http://www.w3.org/2001/XMLSchema-instance"/>
                            <ns3:operationSequence xsi:nil="true" xmlns:xsi="http://www.w3.org/2001/XMLSchema-instance"/>
                            <ns3:theAirspaceVolume>
                                <ns3:AirspaceVolume>
                                    <ns3:minimumLimit uom="FT">3100</ns3:minimumLimit>
                                    <ns3:minimumLimitReference>MSL</ns3:minimumLimitReference>
                                    <ns3:horizontalProjection>
                                        <ns3:Surface srsName="urn:ogc:def:crs:OGC:1.3:CRS84" ns1:id="92b58a97-47ce-4037-b9ef-0b9568fdd753">
                                            <ns1:patches>
                                                <ns1:PolygonPatch interpolation="planar">
                                                    <ns1:exterior>
                                                        <ns1:LinearRing>
                                                            <ns1:posList>-92.22525 33.12895 -92.22822 33.12888 -92.23118 33.12869 -92.23413 33.12838 -92.23706 33.12794 -92.23995 33.12739 -92.24282 33.12672 -92.24563 33.12593 -92.2484 33.12502 -92.25111 33.12401 -92.25376 33.12288 -92.25634 33.12164 -92.25885 33.12031 -92.26127 33.11887 -92.26361 33.11733 -92.26585 33.1157 -92.268 33.11397 -92.27004 33.11216 -92.27197 33.11027 -92.27379 33.10831 -92.27549 33.10627 -92.27708 33.10416 -92.27853 33.10199 -92.27986 33.09976 -92.28105 33.09748 -92.28211 33.09516 -92.28303 33.09279 -92.28382 33.09039 -92.28446 33.08796 -92.28496 33.0855 -92.28531 33.08303 -92.28552 33.08055 -92.28558 33.07806 -92.2855 33.07557 -92.28527 33.07308 -92.28489 33.07061 -92.28437 33.06816 -92.28371 33.06573 -92.28291 33.06334 -92.28197 33.06097 -92.28089 33.05865 -92.27968 33.05638 -92.27833 33.05416 -92.27686 33.052 -92.27526 33.0499 -92.27354 33.04787 -92.2717 33.04591 -92.26975 33.04403 -92.2677 33.04223 -92.26554 33.04052 -92.26328 33.0389 -92.26093 33.03737 -92.2585 33.03594 -92.25598 33.03462 -92.25339 33.0334 -92.25073 33.03229 -92.24801 33.03129 -92.24523 33.0304 -92.24241 33.02962 -92.23954 33.02897 -92.23664 33.02843 -92.23371 33.02801 -92.23076 33.02772 -92.2278 33.02754 -92.22525 33.02749 -92.22228 33.02756 -92.21932 33.02775 -92.21637 33.02807 -92.21344 33.0285 -92.21055 33.02905 -92.20768 33.02973 -92.20487 33.03052 -92.2021 33.03142 -92.19939 33.03244 -92.19674 33.03357 -92.19416 33.0348 -92.19165 33.03614 -92.18923 33.03758 -92.18689 33.03912 -92.18465 33.04076 -92.1825 33.04248 -92.18046 33.04429 -92.17853 33.04618 -92.17671 33.04815 -92.17501 33.05019 -92.17342 33.0523 -92.17197 33.05447 -92.17064 33.0567 -92.16945 33.05898 -92.16839 33.06131 -92.16747 33.06368 -92.16668 33.06608 -92.16604 33.06851 -92.16554 33.07097 -92.16519 33.07344 -92.16498 33.07592 -92.16492 33.07841 -92.165 33.0809 -92.16523 33.08338 -92.16561 33.08585 -92.16613 33.08831 -92.16679 33.09073 -92.16759 33.09313 -92.16853 33.09549 -92.16961 33.09781 -92.17082 33.10008 -92.17217 33.1023 -92.17364 33.10446 -92.17524 33.10656 -92.17696 33.10859 -92.1788 33.11055 -92.18075 33.11243 -92.1828 33.11422 -92.18496 33.11593 -92.18722 33.11755 -92.18957 33.11908 -92.192 33.1205 -92.19452 33.12183 -92.19711 33.12305 -92.19977 33.12416 -92.20249 33.12516 -92.20527 33.12605 -92.20809 33.12682 -92.21096 33.12747 -92.21386 33.12801 -92.21679 33.12843 -92.21974 33.12872 -92.2227 33.1289 -92.22525 33.12895</ns1:posList>
                                                        </ns1:LinearRing>
                                                    </ns1:exterior>
                                                </ns1:PolygonPatch>
                                            </ns1:patches>
                                        </ns3:Surface>
                                    </ns3:horizontalProjection>
                                </ns3:AirspaceVolume>
                            </ns3:theAirspaceVolume>
                        </ns3:AirspaceGeometryComponent>
                    </ns3:geometryComponent>
                </ns3:AirspaceTimeSlice>
            </ns3:timeSlice>
        </ns3:Airspace>
    </ns8:hasMember>
    <ns8:hasMember ns2:type="simple">
        <ns3:Airspace ns1:id="19336117">
            <ns1:description ns2:type="simple">MINIMUM VECTORING ALTITUDE (MVA)</ns1:description>
            <ns1:boundedBy xsi:nil="true" xmlns:xsi="http://www.w3.org/2001/XMLSchema-instance"/>
            <ns3:timeSlice>
                <ns3:AirspaceTimeSlice>
                    <ns1:validTime ns2:type="simple">
                        <ns1:TimePeriod>
                            <ns1:beginPosition>1980-01-01T14:00:00Z</ns1:beginPosition>
                            <ns1:endPosition indeterminatePosition="unknown"/>
                        </ns1:TimePeriod>
                    </ns1:validTime>
                    <ns3:interpretation>BASELINE</ns3:interpretation>
                    <ns3:sequenceNumber>1</ns3:sequenceNumber>
                    <ns3:type>OTHER</ns3:type>
                    <ns3:designator xsi:nil="true" xmlns:xsi="http://www.w3.org/2001/XMLSchema-instance"/>
                    <ns3:localType xsi:nil="true" xmlns:xsi="http://www.w3.org/2001/XMLSchema-instance"/>
                    <ns3:name>H</ns3:name>
                    <ns3:designatorICAO xsi:nil="true" xmlns:xsi="http://www.w3.org/2001/XMLSchema-instance"/>
                    <ns3:controlType xsi:nil="true" xmlns:xsi="http://www.w3.org/2001/XMLSchema-instance"/>
                    <ns3:upperLowerSeparation xsi:nil="true" xmlns:xsi="http://www.w3.org/2001/XMLSchema-instance"/>
                    <ns3:protectedRoute xsi:nil="true" xmlns:xsi="http://www.w3.org/2001/XMLSchema-instance"/>
                    <ns3:geometryComponent>
                        <ns3:AirspaceGeometryComponent>
                            <ns3:operation xsi:nil="true" xmlns:xsi="http://www.w3.org/2001/XMLSchema-instance"/>
                            <ns3:operationSequence xsi:nil="true" xmlns:xsi="http://www.w3.org/2001/XMLSchema-instance"/>
                            <ns3:theAirspaceVolume>
                                <ns3:AirspaceVolume>
                                    <ns3:minimumLimit uom="FT">2000</ns3:minimumLimit>
                                    <ns3:minimumLimitReference>MSL</ns3:minimumLimitReference>
                                    <ns3:horizontalProjection>
                                        <ns3:Surface srsName="urn:ogc:def:crs:OGC:1.3:CRS84" ns1:id="7ea892b4-2943-4738-af24-040ac68cd84a">
                                            <ns1:patches>
                                                <ns1:PolygonPatch interpolation="planar">
                                                    <ns1:exterior>
                                                        <ns1:LinearRing>
                                                            <ns1:posList>-92.03835 32.62858 -92.03658 32.63058 -92.03492 32.63264 -92.03339 32.63477 -92.03199 32.63697 -92.03071 32.63922 -92.02957 32.64151 -92.02856 32.64386 -92.02769 32.64624 -92.02696 32.64865 -92.02637 32.6511 -92.02593 32.65356 -92.02562 32.65604 -92.02547 32.65853 -92.02545 32.66102 -92.02559 32.66351 -92.02587 32.66599 -92.02629 32.66845 -92.02686 32.6709 -92.02756 32.67332 -92.02841 32.6757 -92.0294 32.67805 -92.03052 32.68036 -92.03177 32.68261 -92.03316 32.68481 -92.03467 32.68695 -92.0363 32.68903 -92.03806 32.69104 -92.03914 32.69218 -92.03725 32.69412 -92.03526 32.69598 -92.03315 32.69775 -92.03095 32.69944 -92.02865 32.70103 -92.02626 32.70253 -92.02378 32.70392 -92.02123 32.70521 -92.01861 32.7064 -92.01591 32.70747 -92.01316 32.70843 -92.01036 32.70928 -92.00751 32.71001 -92.00462 32.71062 -92.0017 32.71112 -91.99876 32.71149 -91.99579 32.71173 -91.99282 32.71186 -91.98984 32.71186 -91.98686 32.71174 -91.9839 32.7115 -91.98095 32.71114 -91.97803 32.71065 -91.97514 32.71004 -91.97229 32.70932 -91.96948 32.70848 -91.96673 32.70752 -91.96404 32.70645 -91.96141 32.70528 -91.95885 32.70399 -91.95637 32.7026 -91.95398 32.70111 -91.95167 32.69952 -91.94946 32.69784 -91.94736 32.69607 -91.94535 32.69421 -91.94346 32.69228 -91.94168 32.69027 -91.94003 32.68818 -91.93849 32.68604 -91.93708 32.68383 -91.93581 32.68156 -91.93466 32.67925 -91.93366 32.67689 -91.93279 32.67449 -91.93206 32.67206 -91.93148 32.6696 -91.93104 32.66712 -91.93074 32.66462 -91.93059 32.66212 -91.93059 32.65961 -91.93073 32.65711 -91.93102 32.65461 -91.93145 32.65213 -91.93203 32.64967 -91.93275 32.64724 -91.93361 32.64484 -91.93461 32.64247 -91.93575 32.64016 -91.93702 32.63789 -91.93842 32.63567 -91.93995 32.63352 -91.9416 32.63143 -91.94337 32.62942 -91.94526 32.62748 -91.94725 32.62561 -91.94936 32.62384 -91.95156 32.62215 -91.95386 32.62056 -91.95625 32.61906 -91.95873 32.61766 -91.96128 32.61637 -91.9639 32.61519 -91.96659 32.61411 -91.96935 32.61315 -91.97215 32.6123 -91.975 32.61157 -91.97789 32.61096 -91.98081 32.61046 -91.98375 32.61009 -91.98672 32.60984 -91.98969 32.60972 -91.99267 32.60971 -91.99564 32.60983 -91.99861 32.61008 -92.00156 32.61044 -92.00448 32.61093 -92.00737 32.61154 -92.01022 32.61226 -92.01302 32.6131 -92.01578 32.61406 -92.01847 32.61513 -92.0211 32.61631 -92.02366 32.6176 -92.02614 32.61899 -92.02853 32.62048 -92.03083 32.62207 -92.03304 32.62375 -92.03515 32.62552 -92.03716 32.62738 -92.03835 32.62858</ns1:posList>
                                                        </ns1:LinearRing>
                                                    </ns1:exterior>
                                                </ns1:PolygonPatch>
                                            </ns1:patches>
                                        </ns3:Surface>
                                    </ns3:horizontalProjection>
                                </ns3:AirspaceVolume>
                            </ns3:theAirspaceVolume>
                        </ns3:AirspaceGeometryComponent>
                    </ns3:geometryComponent>
                </ns3:AirspaceTimeSlice>
            </ns3:timeSlice>
        </ns3:Airspace>
    </ns8:hasMember>
</ns8:AIXMBasicMessage>
